{"taskId":"c3a55cfd-cdb1-4791-be3e-580145589535","taskList":{"taskId":"c3a55cfd-cdb1-4791-be3e-580145589535","taskdata":1,"deviceTypeId":"922b13e6-d82d-11e9-9e80-00163e010059","TYPE":0,"category":1,"name":"X射线透视设备","mainType":1,"testProjectList":"[{\"testProjectName\":\"project_fs_fh\",\"testProjectArr\":[{\"name\":\"projcet_gzwyzwtgxdk\"},{\"name\":\"projcet_jfcsl\"},{\"name\":\"projcet_jcjg\"},{\"name\":\"projcet_szpbt\"},{\"name\":\"projcet_gzltj\"},{\"name\":\"projcet_szwjcjlmkt\"},{\"name\":\"projcet_szwjcjlmknr\"},{\"name\":\"projcet_jcbt\"},{\"name\":\"projcet_jcbnr\"},{\"name\":\"projcet_jgyst\"},{\"name\":\"projcet_jgysnr\"}],\"testProjectId\":\"69041af5-ef38-11e9-a9b3-00163e010059\",\"testProjectChineseName\":\"机房周围剂量当量率\",\"testProjectType\":1,\"consumablesName\":null,\"consumablesSize\":0,\"xcStandardName\":\"《医用X射线诊断放射防护要求》\",\"testProjectNum\":\"GBZ 130-2013\",\"xcStandardNum\":\"GBZ 130-2013\",\"standardUseTerms\":\"7.2\",\"detectionLimitPieces\":\"null\",\"planTestingSize\":1,\"toShow\":true,\"blankSize\":0,\"name\":\"project_fs_fh\"},{\"testProjectName\":\"project_ts_tssjzrstbkqbsdnldxz\",\"testProjectArr\":[{\"name\":\"project_ts_tssjzrstbkqbsdnldxz1\"},{\"name\":\"project_ts_tssjzrstbkqbsdnldxz2\"}],\"testProjectId\":\"fabac3dd-6b1d-11ea-831a-00163e067057\",\"testProjectChineseName\":\"透视-透视受检者入射体表空气比释动能率典型值\",\"testProjectType\":1,\"consumablesName\":null,\"consumablesSize\":0,\"xcStandardName\":\"《医用常规X射线诊断设备质量控制检测规范》\",\"testProjectNum\":\"001235\",\"xcStandardNum\":\"WS 76-2017\",\"standardUseTerms\":\"（7.1）\",\"detectionLimitPieces\":\"\",\"planTestingSize\":1,\"toShow\":true,\"blankSize\":0,\"name\":\"project_ts_tssjzrstbkqbsdnldxz\"},{\"testProjectName\":\"project_ts_tssjzrstbkqbsdnlzdz\",\"testProjectArr\":[{\"name\":\"project_ts_tssjzrstbkqbsdnlzdz1\"},{\"name\":\"project_ts_tssjzrstbkqbsdnlzdz2\"}],\"testProjectId\":\"100e50c6-6b1e-11ea-831a-00163e067057\",\"testProjectChineseName\":\"透视-透视受检者入射体表空气比释动能率最大值\",\"testProjectType\":1,\"consumablesName\":null,\"consumablesSize\":0,\"xcStandardName\":\"《医用常规X射线诊断设备质量控制检测规范》\",\"testProjectNum\":\"001523\",\"xcStandardNum\":\"WS 76-2017\",\"standardUseTerms\":\"（7.2）\",\"detectionLimitPieces\":\"\",\"planTestingSize\":1,\"toShow\":true,\"blankSize\":0,\"name\":\"project_ts_tssjzrstbkqbsdnlzdz\"},{\"testProjectName\":\"project_ts_tsygplmd\",\"testProjectArr\":[{\"name\":\"project_ts_tsygplmd1\"},{\"name\":\"project_ts_tsygplmd2\"}],\"testProjectId\":\"2421cb45-6b1e-11ea-831a-00163e067057\",\"testProjectChineseName\":\"透视-透视荧光屏灵敏度\",\"testProjectType\":1,\"consumablesName\":null,\"consumablesSize\":0,\"xcStandardName\":\"《医用常规X射线诊断设备质量控制检测规范》\",\"testProjectNum\":\"464611\",\"xcStandardNum\":\"WS 76-2017\",\"standardUseTerms\":\"（7.3）\",\"detectionLimitPieces\":\"\",\"planTestingSize\":1,\"toShow\":true,\"blankSize\":0,\"name\":\"project_ts_tsygplmd\"},{\"testProjectName\":\"projcet_ts_kjfbl\",\"testProjectArr\":[{\"name\":\"projcet_ts_kjfbl1\"},{\"name\":\"projcet_ts_kjfbl2\"}],\"testProjectId\":\"37cd3a5a-6b1e-11ea-831a-00163e067057\",\"testProjectChineseName\":\"透视-空间分辨力\",\"testProjectType\":1,\"consumablesName\":null,\"consumablesSize\":0,\"xcStandardName\":\"《医用常规X射线诊断设备质量控制检测规范》\",\"testProjectNum\":\"144254\",\"xcStandardNum\":\"WS 76-2017\",\"standardUseTerms\":\"（7.5）\",\"detectionLimitPieces\":\"\",\"planTestingSize\":1,\"toShow\":true,\"blankSize\":0,\"name\":\"projcet_ts_kjfbl\"},{\"testProjectName\":\"project_ts_ddbfbl\",\"testProjectArr\":[{\"name\":\"project_ts_ddbfbl1\"},{\"name\":\"project_ts_ddbfbl2\"}],\"testProjectId\":\"49782881-6b1e-11ea-831a-00163e067057\",\"testProjectChineseName\":\"透视-低对比分辨力\",\"testProjectType\":1,\"consumablesName\":null,\"consumablesSize\":0,\"xcStandardName\":\"《医用常规X射线诊断设备质量控制检测规范》\",\"testProjectNum\":\"4946113\",\"xcStandardNum\":\"WS 76-2017\",\"standardUseTerms\":\"（7.5）\",\"detectionLimitPieces\":\"\",\"planTestingSize\":1,\"toShow\":true,\"blankSize\":0,\"name\":\"project_ts_ddbfbl\"},{\"testProjectName\":\"project_ts_yxjsqrspqkqbsdnl\",\"testProjectArr\":[{\"name\":\"project_ts_yxjsqrspqkqbsdnl1\"},{\"name\":\"project_ts_yxjsqrspqkqbsdnl2\"}],\"testProjectId\":\"5b0e081f-6b1e-11ea-831a-00163e067057\",\"testProjectChineseName\":\"透视-影像接收器入射屏前空气比释动能率\",\"testProjectType\":1,\"consumablesName\":null,\"consumablesSize\":0,\"xcStandardName\":\"《医用常规X射线诊断设备质量控制检测规范》\",\"testProjectNum\":\"4646131\",\"xcStandardNum\":\"WS 76-2017\",\"standardUseTerms\":\"（7.6）\",\"detectionLimitPieces\":\"\",\"planTestingSize\":1,\"toShow\":true,\"blankSize\":0,\"name\":\"project_ts_yxjsqrspqkqbsdnl\"},{\"testProjectName\":\"project_ts_zdldkz\",\"testProjectArr\":[{\"name\":\"project_ts_zdldkz1\"},{\"name\":\"project_ts_zdldkz2\"}],\"testProjectId\":\"6d24a4ac-6b1e-11ea-831a-00163e067057\",\"testProjectChineseName\":\"透视-自动亮度控制\",\"testProjectType\":1,\"consumablesName\":null,\"consumablesSize\":0,\"xcStandardName\":\"《医用常规X射线诊断设备质量控制检测规范》\",\"testProjectNum\":\"6461\",\"xcStandardNum\":\"WS 76-2017\",\"standardUseTerms\":\"（7.7）\",\"detectionLimitPieces\":\"\",\"planTestingSize\":1,\"toShow\":true,\"blankSize\":0,\"name\":\"project_ts_zdldkz\"},{\"testProjectName\":\"project_ts_zsyyyxjsqzxpc\",\"testProjectArr\":null,\"testProjectId\":\"83148145-6b1e-11ea-831a-00163e067057\",\"testProjectChineseName\":\"透视-照射野与影像接收器中心偏差\",\"testProjectType\":1,\"consumablesName\":null,\"consumablesSize\":0,\"xcStandardName\":\"《医用常规X射线诊断设备质量控制检测规范》\",\"testProjectNum\":\"4611\",\"xcStandardNum\":\"WS 76-2017\",\"standardUseTerms\":\"（7.8）\",\"detectionLimitPieces\":\"\",\"planTestingSize\":1,\"toShow\":true,\"blankSize\":0,\"name\":\"project_ts_zsyyyxjsqzxpc\"},{\"testProjectName\":\"project_ts_zdzsyyptygccxtsdhpj\",\"testProjectArr\":null,\"testProjectId\":\"97635d6e-6b1e-11ea-831a-00163e067057\",\"testProjectChineseName\":\"透视-最大照射野与普通荧光屏尺寸相同时的台屏距\",\"testProjectType\":1,\"consumablesName\":null,\"consumablesSize\":0,\"xcStandardName\":\"《医用常规X射线诊断设备质量控制检测规范》\",\"testProjectNum\":\"761251\",\"xcStandardNum\":\"WS 76-2017\",\"standardUseTerms\":\"（1.0）\",\"detectionLimitPieces\":\"\",\"planTestingSize\":1,\"toShow\":true,\"blankSize\":0,\"name\":\"project_ts_zdzsyyptygccxtsdhpj\"}]","sampleSource":0,"sampleCategory":"","assessArr":"[{\"id\":\"59189d2a-8050-11ea-831a-00163e067057\",\"createtime\":\"2020-04-17 10:08:36\",\"testProjectId\":\"100e50c6-6b1e-11ea-831a-00163e067057\",\"evaluateName\":\"WS 76《医用常规X射线诊断设备质量控制检测规范》\",\"evaluateProjectName\":\"WS 76《医用常规X射线诊断设备质量控制检测规范》\",\"standardValue\":\"50\",\"deviceTypesId\":\"a20acffb-d82d-11e9-9e80-00163e010059\",\"deviceMainId\":\"1\"}]","checkDeviceModel":"","checkDeviceName":"","checkDeviceNum":"","checkDeviceVender":"","checkUnitAddress":"浙江省杭州市余杭区未来科技处","checkUnitContact":"1","checkUnitName":"测试的部门1","checkUnitPhone":"1","clientUnitAddress":"浙江省杭州市余杭区未来科技处","clientUnitContact":"","clientUnitName":"测试的部门1","docNum":"","docPass":0,"expectTime":"","monitorType":"","note":"","pass":"未通过","projectId":"6c9393e6-ba16-11ea-831a-00163e067057","subCompanyId":"1","docReason":null,"isBc":1,"isDone":1,"testingPurpose":"卫生验收","address":"浙江省杭州市余杭区未来科技处","createtime":"2020-06-29 22:45:20","needTime":"2020-06-29 22:45:25","endTime":"2020-06-30 11:04:55","checkTime":"2020-06-30 11:05:12","uploadTime":null,"pointUrl":null,"unitUrl":null,"isDocImg":0,"reason":"测"},"getQueryByDeviceTypeName":{"success":true,"msg":"查询成功","datas":[{"num":7,"deviceTypeName":"X射线透视设备","deviceOperations":[{"name":"隔室操作"}],"types":[{"name":"普通荧光屏设备","exposures":[{"name":"直接透视"}]},{"name":"非透视荧光屏设备","exposures":[{"name":"间接透视"}]}]}]},"device":{"success":true,"msg":"查询成功","deviceTypeId":"922b13e6-d82d-11e9-9e80-00163e010059","data":[{"id":"1f0e69c3-8ca5-4b1d-9f41-e51aa0ac3d27","correctNum":"2019H00-10-2208576001","correctTime":"2020-12-09 00:00:00","correctUrl":"/upload/device/RF探头有效期：2019.12.3-2020.12.2.pdf","createtime":"2020-01-10 19:42:24","deviceName":"X射线机质控检测仪","deviceNum":"209590（杭州性能）","deviceUnit":"上海市计量测试技术研究院","probeName":"摄影/透视探头","probeNum":"261035","deviceManufactor":"Unfors RaySafe","type":0,"alpha":null,"beta":null,"deviceFactor1":null,"deviceFactor2":null,"deviceFactor3":null,"deviceFactor4":null,"deviceFactor5":null,"equivalentRate1":null,"equivalentRate2":null,"equivalentRate3":null,"equivalentRate4":null,"factor1":null,"factor2":null,"factor3":null,"factor4":null,"vol1":null,"vol2":null,"vol3":null,"vol4":null,"vol5":null,"deviceModel":"X2","deviceLower":"","lowerTime":null,"lowerUrl":null,"subCompanyId":"1","state":0,"useState":0,"purpose":"性能","deviceFactor":[{"value":"60/1.042","key":1578563471520},{"value":"70/1.035","key":1578563499551},{"value":"80/1.007","key":1578563507402},{"value":"100/0.997","key":1578563521640},{"value":"135/1.008","key":1578563550151}],"factor":null,"vol":null,"correctNum1":"2019H00-10-2208576001","correctTime1":"2020-12-09 00:00:00","correctUrl1":"/upload/device/RF探头有效期：2019.12.3-2020.12.2.pdf","deviceFactor_gdy":[{"value":"39.7/1.0075567","key":1578563575402},{"value":"50/1","key":1578563613087},{"value":"60.5/1.0049587","key":1578563621854},{"value":"70.3/1.009957326","key":1578563622997},{"value":"80.6/1.004962779","key":1578563623937},{"value":"90.90/0.99889989","key":1578563624754},{"value":"101.10 /0.99901088","key":1578563690850},{"value":"111.20/0.997302158","key":1578563712633},{"value":"121.50 /0.995884774","key":1578563743086}],"lowerUnit":null,"staffId":"c4e0be0f-b9ba-11e9-9e80-00163e010059","place":"深圳仪器设备房","metrologyRange":null,"accuracy":null,"metrologyTraceability":null,"testConclusion":null,"calibrationMethod":null,"usageRequirement":null,"calibrationRequirements":"","acceptanceSituation":"合格","acceptanceDocUrl":"/upload/device/购买合同.docx","deviceSource":"购买","deviceSourceUrl":"/upload/device/购买合同.docx","isTestCalibration":null,"correctCalibration":[0,1],"fzContainDeviceArr":null,"activityResponse_a":null,"activityResponse_b":null,"factor_zz":null,"frequency":null,"sysDeviceType":0,"testProjectId":"37cd3a5a-6b1e-11ea-831a-00163e067057"},{"id":"41419363-1128-4bb3-94a0-6dfc5bf6b8f2","correctNum":null,"correctTime":"2020-07-27 08:00:00","correctUrl":null,"createtime":"2020-04-28 13:53:23","deviceName":"湘亭实验室测试设备","deviceNum":"XT006","deviceUnit":null,"probeName":null,"probeNum":null,"deviceManufactor":"杭州湘亭科技有限公司","type":0,"alpha":null,"beta":null,"deviceFactor1":null,"deviceFactor2":null,"deviceFactor3":null,"deviceFactor4":null,"deviceFactor5":null,"equivalentRate1":null,"equivalentRate2":null,"equivalentRate3":null,"equivalentRate4":null,"factor1":null,"factor2":null,"factor3":null,"factor4":null,"vol1":null,"vol2":null,"vol3":null,"vol4":null,"vol5":null,"deviceModel":"XT","deviceLower":"","lowerTime":null,"lowerUrl":null,"subCompanyId":"1","state":0,"useState":0,"purpose":"实验室","deviceFactor":null,"factor":null,"vol":null,"correctNum1":null,"correctTime1":null,"correctUrl1":null,"deviceFactor_gdy":null,"lowerUnit":null,"staffId":null,"place":null,"metrologyRange":null,"accuracy":null,"metrologyTraceability":null,"testConclusion":null,"calibrationMethod":null,"usageRequirement":null,"calibrationRequirements":"1","acceptanceSituation":"合格","acceptanceDocUrl":null,"deviceSource":"购买","deviceSourceUrl":null,"isTestCalibration":null,"correctCalibration":null,"fzContainDeviceArr":null,"activityResponse_a":null,"activityResponse_b":null,"factor_zz":null,"frequency":null,"sysDeviceType":0,"testProjectId":"100e50c6-6b1e-11ea-831a-00163e067057"},{"id":"70d51bac-b98d-4a37-8e5c-e5b39a08d380","correctNum":"DLj12020-00117","correctTime":"2021-01-06 00:00:00","correctUrl":"/upload/device/2222.png","createtime":"2020-06-28 10:36:37","deviceName":"X射线机质控检测仪","deviceNum":"274481+273457-1","deviceUnit":"中国计量科学研究院","probeName":"摄影/透视探头","probeNum":"273457","deviceManufactor":"FLUKE","type":0,"alpha":null,"beta":null,"deviceFactor1":null,"deviceFactor2":null,"deviceFactor3":null,"deviceFactor4":null,"deviceFactor5":null,"equivalentRate1":null,"equivalentRate2":null,"equivalentRate3":null,"equivalentRate4":null,"factor1":null,"factor2":null,"factor3":null,"factor4":null,"vol1":null,"vol2":null,"vol3":null,"vol4":null,"vol5":null,"deviceModel":"X2","deviceLower":"","lowerTime":null,"lowerUrl":null,"subCompanyId":"1","state":0,"useState":0,"purpose":"性能","deviceFactor":[{"value":"50/1.01","key":1591440250245},{"value":"70/1.00","key":1591440252641},{"value":"100/0.98","key":1591440253377},{"value":"120/0.98","key":1591440254033}],"factor":null,"vol":null,"correctNum1":"DLj12020-00118","correctTime1":"2021-01-06 00:00:00","correctUrl1":"/upload/device/2222.png","deviceFactor_gdy":[{"value":"59.60/1.008","key":1591437044451},{"value":"79.50/1.011","key":1591437045435},{"value":"99.41/1.001","key":1591437046539},{"value":"119.37/1.005","key":1591437058719}],"lowerUnit":null,"staffId":"d1b127d4-32ab-11ea-b462-00163e067057","place":"公司设备房","metrologyRange":null,"accuracy":null,"metrologyTraceability":null,"testConclusion":null,"calibrationMethod":null,"usageRequirement":null,"calibrationRequirements":"","acceptanceSituation":"合格","acceptanceDocUrl":"/upload/device/2222.png","deviceSource":"购买","deviceSourceUrl":"/upload/device/2222.png","isTestCalibration":null,"correctCalibration":[1,0],"fzContainDeviceArr":null,"activityResponse_a":null,"activityResponse_b":null,"factor_zz":null,"frequency":null,"sysDeviceType":0,"testProjectId":null},{"id":"a1ae7fd3-84eb-4a17-bcc3-9879f5e16341","correctNum":"2019H21-20-2078835001","correctTime":"2020-10-08 00:00:00","correctUrl":"/upload/device/AT1121-44446 X射线场（有效期2019.10.9-2020.10.8）.pdf","createtime":"2020-01-10 18:21:10","deviceName":"核辐射检测仪","deviceNum":"44446（杭州防护）","deviceUnit":"上海市计量测试计量研究院","probeName":null,"probeNum":null,"deviceManufactor":"ATOMTEX","type":0,"alpha":null,"beta":null,"deviceFactor1":null,"deviceFactor2":null,"deviceFactor3":null,"deviceFactor4":null,"deviceFactor5":null,"equivalentRate1":null,"equivalentRate2":null,"equivalentRate3":null,"equivalentRate4":null,"factor1":null,"factor2":null,"factor3":null,"factor4":null,"vol1":null,"vol2":null,"vol3":null,"vol4":null,"vol5":null,"deviceModel":"AT1121","deviceLower":"0.15μsv/h","lowerTime":"2020-01-09 00:00:00","lowerUrl":"/upload/device/购买合同.docx","subCompanyId":"1","state":0,"useState":0,"purpose":"防护","deviceFactor":[{"value":"80/1.07","key":1578563014366},{"value":"100/1.14","key":1578563102648},{"value":"150/1.09","key":1578563125335},{"value":"200/1.10","key":1578563133301}],"factor":[{"measure1":"1.10","measure2":""}],"vol":null,"correctNum1":"2019H21-20-2078835001","correctTime1":"2020-10-08 00:00:00","correctUrl1":"/upload/device/AT1121-44446 X射线场（有效期2019.10.9-2020.10.8）.pdf","deviceFactor_gdy":null,"lowerUnit":null,"staffId":"c4e0be0f-b9ba-11e9-9e80-00163e010059","place":"深圳仪器设备间","metrologyRange":null,"accuracy":null,"metrologyTraceability":null,"testConclusion":null,"calibrationMethod":"","usageRequirement":null,"calibrationRequirements":"/","acceptanceSituation":"合格","acceptanceDocUrl":"/upload/device/验收报告.docx","deviceSource":"购买","deviceSourceUrl":"/upload/device/购买合同.docx","isTestCalibration":null,"correctCalibration":[["0","1"],[],[]],"fzContainDeviceArr":null,"activityResponse_a":null,"activityResponse_b":null,"factor_zz":null,"frequency":null,"sysDeviceType":0,"testProjectId":"100e50c6-6b1e-11ea-831a-00163e067057"},{"id":"f03a389e-1b22-4508-b465-45301ac81ccf","correctNum":"2019H21-20-2078835001","correctTime":"2020-10-08 00:00:00","correctUrl":"/upload/device/AT1121-44446 X射线场（有效期2019.10.9-2020.10.8）.pdf","createtime":"2019-10-30 21:48:26","deviceName":"核辐射检测仪","deviceNum":"44446","deviceUnit":"上海市计量测试技术研究院","probeName":null,"probeNum":"1112","deviceManufactor":"ATOMTEX","type":0,"alpha":null,"beta":null,"deviceFactor1":null,"deviceFactor2":null,"deviceFactor3":null,"deviceFactor4":null,"deviceFactor5":null,"equivalentRate1":null,"equivalentRate2":null,"equivalentRate3":null,"equivalentRate4":null,"factor1":null,"factor2":null,"factor3":null,"factor4":null,"vol1":null,"vol2":null,"vol3":null,"vol4":null,"vol5":null,"deviceModel":"AT1121","deviceLower":"0.15μSv/h","lowerTime":"2020-10-08 00:00:00","lowerUrl":"/upload/device/购买合同.docx","subCompanyId":"1","state":0,"useState":0,"purpose":"防护","deviceFactor":[{"value":"80/1.07","key":1572443265583},{"value":"100/1.14","key":1572443274594},{"value":"150/1.09","key":1572443281894},{"value":"200/1.10","key":1572443287879}],"factor":[{"measure1":"0.007/1.1","measure2":""}],"vol":null,"correctNum1":"2019H21-20-2078835001","correctTime1":"2020-10-08 00:00:00","correctUrl1":"/upload/device/AT1121-44446 X射线场（有效期2019.10.9-2020.10.8）.pdf","deviceFactor_gdy":null,"lowerUnit":null,"staffId":"c4e0be0f-b9ba-11e9-9e80-00163e010059","place":"深圳仪器设备房","metrologyRange":null,"accuracy":null,"metrologyTraceability":null,"testConclusion":null,"calibrationMethod":"测量值/修正值","usageRequirement":null,"calibrationRequirements":"/","acceptanceSituation":"合格","acceptanceDocUrl":"/upload/device/验收报告.docx","deviceSource":"购买","deviceSourceUrl":"/upload/device/购买合同.docx","isTestCalibration":null,"correctCalibration":[["0","1"],[],[]],"fzContainDeviceArr":null,"activityResponse_a":null,"activityResponse_b":null,"factor_zz":null,"frequency":null,"sysDeviceType":0,"testProjectId":"69041af5-ef38-11e9-a9b3-00163e010059"}],"data_fz":[]},"tasks":{"success":true,"msg":"查询成功","sampleNum_lh":24,"sampleNum_wsw":0,"sampleNum_xczd":1142,"sampleNum_kb":10,"tasks":[{"id":"c3a55cfd-cdb1-4791-be3e-580145589535","sampleSource":0,"sampleCategory":"","assessArr":"[{\"id\":\"59189d2a-8050-11ea-831a-00163e067057\",\"createtime\":\"2020-04-17 10:08:36\",\"testProjectId\":\"100e50c6-6b1e-11ea-831a-00163e067057\",\"evaluateName\":\"WS 76《医用常规X射线诊断设备质量控制检测规范》\",\"evaluateProjectName\":\"WS 76《医用常规X射线诊断设备质量控制检测规范》\",\"standardValue\":\"50\",\"deviceTypesId\":\"a20acffb-d82d-11e9-9e80-00163e010059\",\"deviceMainId\":\"1\"}]","evaluateId":"59189d2a-8050-11ea-831a-00163e067057","checkComputerRoom":"","checkDeviceModel":"","checkDeviceName":"","checkDeviceNum":"","checkDeviceProbe":0,"checkDeviceVender":"","checkUnitAddress":"浙江省杭州市余杭区未来科技处","checkUnitContact":"1","checkUnitName":"测试的部门1","checkUnitPhone":"1","checkStaffId":"7242e444-5abc-11e9-91ed-00163e010059","checkUrl":null,"clientUnitAddress":"浙江省杭州市余杭区未来科技处","clientUnitContact":"","clientUnitName":"测试的部门1","clientUnitPhone":"","entrustTime":null,"confirmUrl":null,"createtime":"2020-06-29 22:45:20","data":"[{\"testProject\":\"project_jbxx\",\"multipleId\":\"0.05830382305254567init0.30036511622910367\",\"entrustedUnitName\":\"测试的部门1\",\"assessArr\":\"WS 76《医用常规X射线诊断设备质量控制检测规范》\",\"UnitExaminationName\":\"测试的部门1\",\"UnitExaminationAddress\":\"浙江省杭州市余杭区未来科技处\",\"detectionObjects\":\"X射线透视设备\",\"purposeDetection\":\"卫生验收\",\"organizationName\":\"深圳市瑞达检测技术有限公司\",\"siteEnvironment2\":\"\",\"siteEnvironment3\":\"\",\"institutionalAddress\":\"深圳市龙华区民治街道上芬社区第五工业区二区4号201\",\"licenseNumber\":\"91440300074380587M\",\"metrologyCertificate\":\"201719120948\",\"detectionTime\":\"2020-06-30  11:58:35\",\"samplingPersonnel\":\"《医用X射线诊断放射防护要求》GBZ 130-2013,《医用常规X射线诊断设备质量控制检测规范》WS 76-2017\",\"fontSize\":14,\"detectionBasis\":\"test1,test2\",\"point\":[{\"rows\":[\"核辐射检测仪\",\"AT1121\",\"44446（杭州防护）\",\"2019H21-20-2078835001+2019H21-20-2078835001\",\"2020/10/08 00:00:00+2020/10/08 00:00:00\",\"a1ae7fd3-84eb-4a17-bcc3-9879f5e16341\"],\"index\":1,\"deviceFactor\":[{\"value\":\"80/1.07\",\"key\":1578563014366},{\"value\":\"100/1.14\",\"key\":1578563102648},{\"value\":\"150/1.09\",\"key\":1578563125335},{\"value\":\"200/1.10\",\"key\":1578563133301}],\"deviceObj\":{\"id\":\"a1ae7fd3-84eb-4a17-bcc3-9879f5e16341\",\"correctNum\":\"2019H21-20-2078835001\",\"correctTime\":\"2020-10-08 00:00:00\",\"correctUrl\":\"/upload/device/AT1121-44446 X射线场（有效期2019.10.9-2020.10.8）.pdf\",\"createtime\":\"2020-01-10 18:21:10\",\"deviceName\":\"核辐射检测仪\",\"deviceNum\":\"44446（杭州防护）\",\"deviceUnit\":\"上海市计量测试计量研究院\",\"probeName\":null,\"probeNum\":null,\"deviceManufactor\":\"ATOMTEX\",\"type\":0,\"alpha\":null,\"beta\":null,\"deviceFactor1\":null,\"deviceFactor2\":null,\"deviceFactor3\":null,\"deviceFactor4\":null,\"deviceFactor5\":null,\"equivalentRate1\":null,\"equivalentRate2\":null,\"equivalentRate3\":null,\"equivalentRate4\":null,\"factor1\":null,\"factor2\":null,\"factor3\":null,\"factor4\":null,\"vol1\":null,\"vol2\":null,\"vol3\":null,\"vol4\":null,\"vol5\":null,\"deviceModel\":\"AT1121\",\"deviceLower\":\"0.15μsv/h\",\"lowerTime\":\"2020-01-09 00:00:00\",\"lowerUrl\":\"/upload/device/购买合同.docx\",\"subCompanyId\":\"1\",\"state\":0,\"useState\":0,\"purpose\":\"防护\",\"deviceFactor\":[{\"value\":\"80/1.07\",\"key\":1578563014366},{\"value\":\"100/1.14\",\"key\":1578563102648},{\"value\":\"150/1.09\",\"key\":1578563125335},{\"value\":\"200/1.10\",\"key\":1578563133301}],\"factor\":[{\"measure1\":\"1.10\",\"measure2\":\"\"}],\"vol\":null,\"correctNum1\":\"2019H21-20-2078835001\",\"correctTime1\":\"2020-10-08 00:00:00\",\"correctUrl1\":\"/upload/device/AT1121-44446 X射线场（有效期2019.10.9-2020.10.8）.pdf\",\"deviceFactor_gdy\":null,\"lowerUnit\":null,\"staffId\":\"c4e0be0f-b9ba-11e9-9e80-00163e010059\",\"place\":\"深圳仪器设备间\",\"metrologyRange\":null,\"accuracy\":null,\"metrologyTraceability\":null,\"testConclusion\":null,\"calibrationMethod\":\"\",\"usageRequirement\":null,\"calibrationRequirements\":\"/\",\"acceptanceSituation\":\"合格\",\"acceptanceDocUrl\":\"/upload/device/验收报告.docx\",\"deviceSource\":\"购买\",\"deviceSourceUrl\":\"/upload/device/购买合同.docx\",\"isTestCalibration\":null,\"correctCalibration\":[[\"0\",\"1\"],[],[]],\"fzContainDeviceArr\":null,\"activityResponse_a\":null,\"activityResponse_b\":null,\"factor_zz\":null,\"frequency\":null,\"sysDeviceType\":0,\"testProjectId\":\"100e50c6-6b1e-11ea-831a-00163e067057\"}},{\"rows\":[\"X射线机质控检测仪\",\"X2\",\"261035+209590（杭州性能）\",\"2019H00-10-2208576001+2019H00-10-2208576001\",\"2020/12/09 00:00:00+2020/12/09 00:00:00\",\"1f0e69c3-8ca5-4b1d-9f41-e51aa0ac3d27\"],\"index\":2,\"deviceFactor\":[{\"value\":\"60/1.042\",\"key\":1578563471520},{\"value\":\"70/1.035\",\"key\":1578563499551},{\"value\":\"80/1.007\",\"key\":1578563507402},{\"value\":\"100/0.997\",\"key\":1578563521640},{\"value\":\"135/1.008\",\"key\":1578563550151}],\"deviceObj\":{\"id\":\"1f0e69c3-8ca5-4b1d-9f41-e51aa0ac3d27\",\"correctNum\":\"2019H00-10-2208576001\",\"correctTime\":\"2020-12-09 00:00:00\",\"correctUrl\":\"/upload/device/RF探头有效期：2019.12.3-2020.12.2.pdf\",\"createtime\":\"2020-01-10 19:42:24\",\"deviceName\":\"X射线机质控检测仪\",\"deviceNum\":\"209590（杭州性能）\",\"deviceUnit\":\"上海市计量测试技术研究院\",\"probeName\":\"摄影/透视探头\",\"probeNum\":\"261035\",\"deviceManufactor\":\"Unfors RaySafe\",\"type\":0,\"alpha\":null,\"beta\":null,\"deviceFactor1\":null,\"deviceFactor2\":null,\"deviceFactor3\":null,\"deviceFactor4\":null,\"deviceFactor5\":null,\"equivalentRate1\":null,\"equivalentRate2\":null,\"equivalentRate3\":null,\"equivalentRate4\":null,\"factor1\":null,\"factor2\":null,\"factor3\":null,\"factor4\":null,\"vol1\":null,\"vol2\":null,\"vol3\":null,\"vol4\":null,\"vol5\":null,\"deviceModel\":\"X2\",\"deviceLower\":\"\",\"lowerTime\":null,\"lowerUrl\":null,\"subCompanyId\":\"1\",\"state\":0,\"useState\":0,\"purpose\":\"性能\",\"deviceFactor\":[{\"value\":\"60/1.042\",\"key\":1578563471520},{\"value\":\"70/1.035\",\"key\":1578563499551},{\"value\":\"80/1.007\",\"key\":1578563507402},{\"value\":\"100/0.997\",\"key\":1578563521640},{\"value\":\"135/1.008\",\"key\":1578563550151}],\"factor\":null,\"vol\":null,\"correctNum1\":\"2019H00-10-2208576001\",\"correctTime1\":\"2020-12-09 00:00:00\",\"correctUrl1\":\"/upload/device/RF探头有效期：2019.12.3-2020.12.2.pdf\",\"deviceFactor_gdy\":[{\"value\":\"39.7/1.0075567\",\"key\":1578563575402},{\"value\":\"50/1\",\"key\":1578563613087},{\"value\":\"60.5/1.0049587\",\"key\":1578563621854},{\"value\":\"70.3/1.009957326\",\"key\":1578563622997},{\"value\":\"80.6/1.004962779\",\"key\":1578563623937},{\"value\":\"90.90/0.99889989\",\"key\":1578563624754},{\"value\":\"101.10 /0.99901088\",\"key\":1578563690850},{\"value\":\"111.20/0.997302158\",\"key\":1578563712633},{\"value\":\"121.50 /0.995884774\",\"key\":1578563743086}],\"lowerUnit\":null,\"staffId\":\"c4e0be0f-b9ba-11e9-9e80-00163e010059\",\"place\":\"深圳仪器设备房\",\"metrologyRange\":null,\"accuracy\":null,\"metrologyTraceability\":null,\"testConclusion\":null,\"calibrationMethod\":null,\"usageRequirement\":null,\"calibrationRequirements\":\"\",\"acceptanceSituation\":\"合格\",\"acceptanceDocUrl\":\"/upload/device/购买合同.docx\",\"deviceSource\":\"购买\",\"deviceSourceUrl\":\"/upload/device/购买合同.docx\",\"isTestCalibration\":null,\"correctCalibration\":[0,1],\"fzContainDeviceArr\":null,\"activityResponse_a\":null,\"activityResponse_b\":null,\"factor_zz\":null,\"frequency\":null,\"sysDeviceType\":0,\"testProjectId\":\"37cd3a5a-6b1e-11ea-831a-00163e067057\"}},{\"rows\":[\"\",\"\",\"\",\"\",\"\"],\"index\":3},{\"rows\":[\"\",\"\",\"\",\"\",\"\"],\"index\":4},{\"rows\":[\"\",\"\",\"\",\"\",\"\"],\"index\":5},{\"rows\":[\"\",\"\",\"\",\"\",\"\"],\"index\":6}],\"todayDate\":\"2020年06月30日  11时58分\",\"positionId\":\"40d4331ac8cd0345cf2b5d9eeb3798260693\",\"testProjectChineseName\":\"基本信息\",\"testProjectId\":\"0.21572251051080960.5101380966100115\",\"imgBase64\":\"\",\"imgBase64Two\":\"\",\"imgBase64Three\":\"\",\"deviceData\":[],\"delRowReasonArr\":[],\"deleteArr\":[],\"sampleNum\":\"\",\"sampleNum2\":\"\",\"sampleNum3\":\"\"},{\"testProject\":\"project_jcxcxx\",\"multipleId\":\"0.4214444355669469init0.6351435806712165\",\"deviceName\":\"14\",\"deviceModel\":\"14\",\"deviceNum\":\"14\",\"manufacturer\":\"14\",\"mainParameterkV\":\"1\",\"mainParametermA\":\"1\",\"mainParametermAutil\":\"mA\",\"location\":\"14\",\"ballNum\":\"14\",\"deviceType\":\"普通荧光屏设备\",\"point\":[{\"exposureMode\":\"直接透视\",\"harnessDirection\":\"14\",\"index\":1}],\"deviceStatus\":\"开机\",\"operationMode\":[\"\",true],\"sonOperation\":\"介入操作\",\"surgeonNum\":\"5\",\"siteEnvironment\":\"14\",\"positionId\":\"5fa12e72bc27874e3ef8804b68bb77ba141a\",\"testProjectChineseName\":\"检测现场信息\",\"testProjectId\":\"0.090252355993021730.30098425757015246\",\"deviceData\":[],\"delRowReasonArr\":[],\"deleteArr\":[],\"sampleNum\":\"\",\"sampleNum2\":\"\",\"sampleNum3\":\"\",\"siteEnvironment2\":\"411\",\"siteEnvironment3\":\"4\"},{\"moFold\":false,\"testProject\":\"projcet_gzwyzwtgxdk\",\"testProjectChineseName\":\"机房周围剂量当量率\",\"multipleId\":\"0.9074102794827719init0.3283068085420391\",\"point\":[{\"rows\":[\"工作人员操作位\",\"\",\"\"],\"index\":1},{\"rows\":[\"管线洞口\",\"\",\"\"],\"index\":2}],\"testProjectId\":\"69041af5-ef38-11e9-a9b3-00163e010059\",\"testProjectType\":1,\"detectionLimitPieces\":\"null\",\"xcStandardName\":\"《医用X射线诊断放射防护要求》\",\"xcStandardNum\":\"GBZ 130-2013\",\"standardUseTerms\":\"7.2\",\"positionId\":\"66789a1715d572427fb8384a0cd5c24c7d40\",\"deviceData\":[{\"id\":\"f03a389e-1b22-4508-b465-45301ac81ccf\",\"correctNum\":\"2019H21-20-2078835001\",\"correctTime\":\"2020-10-08 00:00:00\",\"correctUrl\":\"/upload/device/AT1121-44446 X射线场（有效期2019.10.9-2020.10.8）.pdf\",\"createtime\":\"2019-10-30 21:48:26\",\"deviceName\":\"核辐射检测仪\",\"deviceNum\":\"44446\",\"deviceUnit\":\"上海市计量测试技术研究院\",\"probeName\":null,\"probeNum\":\"1112\",\"deviceManufactor\":\"ATOMTEX\",\"type\":0,\"alpha\":null,\"beta\":null,\"deviceFactor1\":null,\"deviceFactor2\":null,\"deviceFactor3\":null,\"deviceFactor4\":null,\"deviceFactor5\":null,\"equivalentRate1\":null,\"equivalentRate2\":null,\"equivalentRate3\":null,\"equivalentRate4\":null,\"factor1\":null,\"factor2\":null,\"factor3\":null,\"factor4\":null,\"vol1\":null,\"vol2\":null,\"vol3\":null,\"vol4\":null,\"vol5\":null,\"deviceModel\":\"AT1121\",\"deviceLower\":\"0.15μSv/h\",\"lowerTime\":\"2020-10-08 00:00:00\",\"lowerUrl\":\"/upload/device/购买合同.docx\",\"subCompanyId\":\"1\",\"state\":0,\"useState\":0,\"purpose\":\"防护\",\"deviceFactor\":[{\"value\":\"80/1.07\",\"key\":1572443265583},{\"value\":\"100/1.14\",\"key\":1572443274594},{\"value\":\"150/1.09\",\"key\":1572443281894},{\"value\":\"200/1.10\",\"key\":1572443287879}],\"factor\":[{\"measure1\":\"0.007/1.1\",\"measure2\":\"\"}],\"vol\":null,\"correctNum1\":\"2019H21-20-2078835001\",\"correctTime1\":\"2020-10-08 00:00:00\",\"correctUrl1\":\"/upload/device/AT1121-44446 X射线场（有效期2019.10.9-2020.10.8）.pdf\",\"deviceFactor_gdy\":null,\"lowerUnit\":null,\"staffId\":\"c4e0be0f-b9ba-11e9-9e80-00163e010059\",\"place\":\"深圳仪器设备房\",\"metrologyRange\":null,\"accuracy\":null,\"metrologyTraceability\":null,\"testConclusion\":null,\"calibrationMethod\":\"测量值/修正值\",\"usageRequirement\":null,\"calibrationRequirements\":\"/\",\"acceptanceSituation\":\"合格\",\"acceptanceDocUrl\":\"/upload/device/验收报告.docx\",\"deviceSource\":\"购买\",\"deviceSourceUrl\":\"/upload/device/购买合同.docx\",\"isTestCalibration\":null,\"correctCalibration\":[[\"0\",\"1\"],[],[]],\"fzContainDeviceArr\":null,\"activityResponse_a\":null,\"activityResponse_b\":null,\"factor_zz\":null,\"frequency\":null,\"sysDeviceType\":0,\"testProjectId\":\"69041af5-ef38-11e9-a9b3-00163e010059\"}],\"carried\":true},{\"testProject\":\"projcet_jfcsl\",\"testProjectChineseName\":\"机房周围剂量当量率\",\"moFold\":false,\"multipleId\":\"0.8094360173864505init0.5644780452079727\",\"point\":[{\"rows\":[\"观察窗\",\"\",\"\",\"\",\"\"],\"index\":1,\"myId\":\"b81e6ce405ba0947c71999299f0fb144a4a1\"}],\"testProjectId\":\"69041af5-ef38-11e9-a9b3-00163e010059\",\"testProjectType\":1,\"detectionLimitPieces\":\"null\",\"xcStandardName\":\"《医用X射线诊断放射防护要求》\",\"xcStandardNum\":\"GBZ 130-2013\",\"standardUseTerms\":\"7.2\",\"positionId\":\"2bf6b422eaf4fc48d458cfc8e09a543872f4\",\"deviceData\":[{\"id\":\"f03a389e-1b22-4508-b465-45301ac81ccf\",\"correctNum\":\"2019H21-20-2078835001\",\"correctTime\":\"2020-10-08 00:00:00\",\"correctUrl\":\"/upload/device/AT1121-44446 X射线场（有效期2019.10.9-2020.10.8）.pdf\",\"createtime\":\"2019-10-30 21:48:26\",\"deviceName\":\"核辐射检测仪\",\"deviceNum\":\"44446\",\"deviceUnit\":\"上海市计量测试技术研究院\",\"probeName\":null,\"probeNum\":\"1112\",\"deviceManufactor\":\"ATOMTEX\",\"type\":0,\"alpha\":null,\"beta\":null,\"deviceFactor1\":null,\"deviceFactor2\":null,\"deviceFactor3\":null,\"deviceFactor4\":null,\"deviceFactor5\":null,\"equivalentRate1\":null,\"equivalentRate2\":null,\"equivalentRate3\":null,\"equivalentRate4\":null,\"factor1\":null,\"factor2\":null,\"factor3\":null,\"factor4\":null,\"vol1\":null,\"vol2\":null,\"vol3\":null,\"vol4\":null,\"vol5\":null,\"deviceModel\":\"AT1121\",\"deviceLower\":\"0.15μSv/h\",\"lowerTime\":\"2020-10-08 00:00:00\",\"lowerUrl\":\"/upload/device/购买合同.docx\",\"subCompanyId\":\"1\",\"state\":0,\"useState\":0,\"purpose\":\"防护\",\"deviceFactor\":[{\"value\":\"80/1.07\",\"key\":1572443265583},{\"value\":\"100/1.14\",\"key\":1572443274594},{\"value\":\"150/1.09\",\"key\":1572443281894},{\"value\":\"200/1.10\",\"key\":1572443287879}],\"factor\":[{\"measure1\":\"0.007/1.1\",\"measure2\":\"\"}],\"vol\":null,\"correctNum1\":\"2019H21-20-2078835001\",\"correctTime1\":\"2020-10-08 00:00:00\",\"correctUrl1\":\"/upload/device/AT1121-44446 X射线场（有效期2019.10.9-2020.10.8）.pdf\",\"deviceFactor_gdy\":null,\"lowerUnit\":null,\"staffId\":\"c4e0be0f-b9ba-11e9-9e80-00163e010059\",\"place\":\"深圳仪器设备房\",\"metrologyRange\":null,\"accuracy\":null,\"metrologyTraceability\":null,\"testConclusion\":null,\"calibrationMethod\":\"测量值/修正值\",\"usageRequirement\":null,\"calibrationRequirements\":\"/\",\"acceptanceSituation\":\"合格\",\"acceptanceDocUrl\":\"/upload/device/验收报告.docx\",\"deviceSource\":\"购买\",\"deviceSourceUrl\":\"/upload/device/购买合同.docx\",\"isTestCalibration\":null,\"correctCalibration\":[[\"0\",\"1\"],[],[]],\"fzContainDeviceArr\":null,\"activityResponse_a\":null,\"activityResponse_b\":null,\"factor_zz\":null,\"frequency\":null,\"sysDeviceType\":0,\"testProjectId\":\"69041af5-ef38-11e9-a9b3-00163e010059\"}],\"carried\":true},{\"testProject\":\"projcet_jcjg\",\"moFold\":false,\"multipleId\":\"0.757926179885176init0.0949856391344126\",\"point\":[{\"rows\":[\"控制室门\",\"\",\"\",\"\",\"\",\"\",\"\"],\"index\":1,\"myId\":\"6010ad0ecff68c4a48586def5b4a8e318223\"},{\"rows\":[\"机房大门\",\"\",\"\",\"\",\"\",\"\",\"\"],\"index\":2,\"myId\":\"9c7c72caacba3b4879c82411fc303e66be2d\"}],\"testProjectId\":\"69041af5-ef38-11e9-a9b3-00163e010059\",\"testProjectType\":1,\"testProjectChineseName\":\"机房周围剂量当量率\",\"detectionLimitPieces\":\"null\",\"xcStandardName\":\"《医用X射线诊断放射防护要求》\",\"xcStandardNum\":\"GBZ 130-2013\",\"standardUseTerms\":\"7.2\",\"positionId\":\"7e28d7d40688684c212a58f35a3000932613\",\"deviceData\":[{\"id\":\"f03a389e-1b22-4508-b465-45301ac81ccf\",\"correctNum\":\"2019H21-20-2078835001\",\"correctTime\":\"2020-10-08 00:00:00\",\"correctUrl\":\"/upload/device/AT1121-44446 X射线场（有效期2019.10.9-2020.10.8）.pdf\",\"createtime\":\"2019-10-30 21:48:26\",\"deviceName\":\"核辐射检测仪\",\"deviceNum\":\"44446\",\"deviceUnit\":\"上海市计量测试技术研究院\",\"probeName\":null,\"probeNum\":\"1112\",\"deviceManufactor\":\"ATOMTEX\",\"type\":0,\"alpha\":null,\"beta\":null,\"deviceFactor1\":null,\"deviceFactor2\":null,\"deviceFactor3\":null,\"deviceFactor4\":null,\"deviceFactor5\":null,\"equivalentRate1\":null,\"equivalentRate2\":null,\"equivalentRate3\":null,\"equivalentRate4\":null,\"factor1\":null,\"factor2\":null,\"factor3\":null,\"factor4\":null,\"vol1\":null,\"vol2\":null,\"vol3\":null,\"vol4\":null,\"vol5\":null,\"deviceModel\":\"AT1121\",\"deviceLower\":\"0.15μSv/h\",\"lowerTime\":\"2020-10-08 00:00:00\",\"lowerUrl\":\"/upload/device/购买合同.docx\",\"subCompanyId\":\"1\",\"state\":0,\"useState\":0,\"purpose\":\"防护\",\"deviceFactor\":[{\"value\":\"80/1.07\",\"key\":1572443265583},{\"value\":\"100/1.14\",\"key\":1572443274594},{\"value\":\"150/1.09\",\"key\":1572443281894},{\"value\":\"200/1.10\",\"key\":1572443287879}],\"factor\":[{\"measure1\":\"0.007/1.1\",\"measure2\":\"\"}],\"vol\":null,\"correctNum1\":\"2019H21-20-2078835001\",\"correctTime1\":\"2020-10-08 00:00:00\",\"correctUrl1\":\"/upload/device/AT1121-44446 X射线场（有效期2019.10.9-2020.10.8）.pdf\",\"deviceFactor_gdy\":null,\"lowerUnit\":null,\"staffId\":\"c4e0be0f-b9ba-11e9-9e80-00163e010059\",\"place\":\"深圳仪器设备房\",\"metrologyRange\":null,\"accuracy\":null,\"metrologyTraceability\":null,\"testConclusion\":null,\"calibrationMethod\":\"测量值/修正值\",\"usageRequirement\":null,\"calibrationRequirements\":\"/\",\"acceptanceSituation\":\"合格\",\"acceptanceDocUrl\":\"/upload/device/验收报告.docx\",\"deviceSource\":\"购买\",\"deviceSourceUrl\":\"/upload/device/购买合同.docx\",\"isTestCalibration\":null,\"correctCalibration\":[[\"0\",\"1\"],[],[]],\"fzContainDeviceArr\":null,\"activityResponse_a\":null,\"activityResponse_b\":null,\"factor_zz\":null,\"frequency\":null,\"sysDeviceType\":0,\"testProjectId\":\"69041af5-ef38-11e9-a9b3-00163e010059\"}],\"carried\":true},{\"testProject\":\"projcet_szpbt\",\"multipleId\":\"0.1572583849009659init0.3597466256663726\",\"moFold\":false,\"point\":[{\"rows\":[\"墙1\",\"\",\"\",\"\",\"\"],\"index\":1},{\"rows\":[\"墙2\",\"\",\"\",\"\",\"\"],\"index\":2},{\"rows\":[\"墙3\",\"\",\"\",\"\",\"\"],\"index\":3},{\"rows\":[\"墙4\",\"\",\"\",\"\",\"\"],\"index\":4},{\"rows\":[\"机房上方\",\"\",\"\",\"\",\"\"],\"index\":5},{\"rows\":[\"机房下方\",\"\",\"\",\"\",\"\"],\"index\":6}],\"testProjectId\":\"69041af5-ef38-11e9-a9b3-00163e010059\",\"testProjectType\":1,\"testProjectChineseName\":\"机房周围剂量当量率\",\"detectionLimitPieces\":\"null\",\"xcStandardName\":\"《医用X射线诊断放射防护要求》\",\"xcStandardNum\":\"GBZ 130-2013\",\"standardUseTerms\":\"7.2\",\"positionId\":\"6c2185acc6ea9d447f88ad64e01942822a10\",\"deviceData\":[{\"id\":\"f03a389e-1b22-4508-b465-45301ac81ccf\",\"correctNum\":\"2019H21-20-2078835001\",\"correctTime\":\"2020-10-08 00:00:00\",\"correctUrl\":\"/upload/device/AT1121-44446 X射线场（有效期2019.10.9-2020.10.8）.pdf\",\"createtime\":\"2019-10-30 21:48:26\",\"deviceName\":\"核辐射检测仪\",\"deviceNum\":\"44446\",\"deviceUnit\":\"上海市计量测试技术研究院\",\"probeName\":null,\"probeNum\":\"1112\",\"deviceManufactor\":\"ATOMTEX\",\"type\":0,\"alpha\":null,\"beta\":null,\"deviceFactor1\":null,\"deviceFactor2\":null,\"deviceFactor3\":null,\"deviceFactor4\":null,\"deviceFactor5\":null,\"equivalentRate1\":null,\"equivalentRate2\":null,\"equivalentRate3\":null,\"equivalentRate4\":null,\"factor1\":null,\"factor2\":null,\"factor3\":null,\"factor4\":null,\"vol1\":null,\"vol2\":null,\"vol3\":null,\"vol4\":null,\"vol5\":null,\"deviceModel\":\"AT1121\",\"deviceLower\":\"0.15μSv/h\",\"lowerTime\":\"2020-10-08 00:00:00\",\"lowerUrl\":\"/upload/device/购买合同.docx\",\"subCompanyId\":\"1\",\"state\":0,\"useState\":0,\"purpose\":\"防护\",\"deviceFactor\":[{\"value\":\"80/1.07\",\"key\":1572443265583},{\"value\":\"100/1.14\",\"key\":1572443274594},{\"value\":\"150/1.09\",\"key\":1572443281894},{\"value\":\"200/1.10\",\"key\":1572443287879}],\"factor\":[{\"measure1\":\"0.007/1.1\",\"measure2\":\"\"}],\"vol\":null,\"correctNum1\":\"2019H21-20-2078835001\",\"correctTime1\":\"2020-10-08 00:00:00\",\"correctUrl1\":\"/upload/device/AT1121-44446 X射线场（有效期2019.10.9-2020.10.8）.pdf\",\"deviceFactor_gdy\":null,\"lowerUnit\":null,\"staffId\":\"c4e0be0f-b9ba-11e9-9e80-00163e010059\",\"place\":\"深圳仪器设备房\",\"metrologyRange\":null,\"accuracy\":null,\"metrologyTraceability\":null,\"testConclusion\":null,\"calibrationMethod\":\"测量值/修正值\",\"usageRequirement\":null,\"calibrationRequirements\":\"/\",\"acceptanceSituation\":\"合格\",\"acceptanceDocUrl\":\"/upload/device/验收报告.docx\",\"deviceSource\":\"购买\",\"deviceSourceUrl\":\"/upload/device/购买合同.docx\",\"isTestCalibration\":null,\"correctCalibration\":[[\"0\",\"1\"],[],[]],\"fzContainDeviceArr\":null,\"activityResponse_a\":null,\"activityResponse_b\":null,\"factor_zz\":null,\"frequency\":null,\"sysDeviceType\":0,\"testProjectId\":\"69041af5-ef38-11e9-a9b3-00163e010059\"}],\"carried\":true},{\"testProject\":\"projcet_jcbt\",\"multipleId\":0,\"isObtain\":true,\"deviceState\":\"开机\",\"exposureMode\":\"直接透视\",\"harnessDirection\":\"14\",\"unit1\":\"mA\",\"unit2\":\"ms\",\"exposureParameterkV1\":\"\",\"exposureParametermA\":\"\",\"exposureParameterms\":\"\",\"exposureParameterkV2\":\"\",\"exposureParametermAs\":\"\",\"exposureParameterState\":\"\",\"irradiationField1\":\"\",\"irradiationField2\":\"\",\"radio\":\"1\",\"calibrationFactor\":\"\",\"Judge\":false,\"point\":[],\"positionId\":\"81371cf1bded5949db888b2e3e816155bca7\",\"testProjectChineseName\":\"防护检测条件\",\"testProjectId\":\"0.55454508668037070.5044634864827113\",\"carried\":true,\"deviceData\":[]},{\"testProject\":\"projcet_jcbnr\",\"multipleId\":0,\"testPoinrNum\":[true,true,true],\"company\":\"μSv/h\",\"testNum\":3,\"isObtain\":true,\"point\":[{\"rows\":[\"观察窗\",\"\",\"\",\"\",\"\",\"\",\"\",\"\",\"\",\"b81e6ce405ba0947c71999299f0fb144a4a1_0\"],\"index\":1},{\"rows\":[\"控制室门\",\"上侧\",\"\",\"\",\"\",\"\",\"\",\"\",\"\",\"6010ad0ecff68c4a48586def5b4a8e318223_0\"],\"index\":2},{\"rows\":[\"控制室门\",\"下侧\",\"\",\"\",\"\",\"\",\"\",\"\",\"\",\"6010ad0ecff68c4a48586def5b4a8e318223_1\"],\"index\":3},{\"rows\":[\"控制室门\",\"左侧\",\"\",\"\",\"\",\"\",\"\",\"\",\"\",\"6010ad0ecff68c4a48586def5b4a8e318223_2\"],\"index\":4},{\"rows\":[\"控制室门\",\"右侧\",\"\",\"\",\"\",\"\",\"\",\"\",\"\",\"6010ad0ecff68c4a48586def5b4a8e318223_3\"],\"index\":5},{\"rows\":[\"控制室门\",\"中部\",\"\",\"\",\"\",\"\",\"\",\"\",\"\",\"6010ad0ecff68c4a48586def5b4a8e318223_4\"],\"index\":6}],\"positionId\":\"a0781b48a418014b6bab32b1b7b45e61f7fd\",\"testProjectChineseName\":\"防护检测数据\",\"testProjectId\":\"0.79766868558589540.7344386131854479\",\"carried\":true,\"deviceData\":[]},{\"testProject\":\"projcet_jcbnr\",\"multipleId\":0,\"testPoinrNum\":[true,true,true],\"company\":\"μSv/h\",\"testNum\":3,\"isObtain\":true,\"point\":[{\"rows\":[\"机房大门\",\"上侧\",\"\",\"\",\"\",\"\",\"\",\"\",\"\",\"9c7c72caacba3b4879c82411fc303e66be2d_0\"],\"index\":7,\"multi\":true,\"multiIndex\":6},{\"rows\":[\"机房大门\",\"下侧\",\"\",\"\",\"\",\"\",\"\",\"\",\"\",\"9c7c72caacba3b4879c82411fc303e66be2d_1\"],\"index\":8},{\"rows\":[\"机房大门\",\"左侧\",\"\",\"\",\"\",\"\",\"\",\"\",\"\",\"9c7c72caacba3b4879c82411fc303e66be2d_2\"],\"index\":9},{\"rows\":[\"机房大门\",\"右侧\",\"\",\"\",\"\",\"\",\"\",\"\",\"\",\"9c7c72caacba3b4879c82411fc303e66be2d_3\"],\"index\":10},{\"rows\":[\"机房大门\",\"中部\",\"\",\"\",\"\",\"\",\"\",\"\",\"\",\"9c7c72caacba3b4879c82411fc303e66be2d_4\"],\"index\":11}],\"positionId\":\"a0781b48a418014b6bab32b1b7b45e61f7fd\",\"testProjectChineseName\":\"防护检测数据\",\"testProjectId\":\"0.79766868558589540.7344386131854479\",\"carried\":true,\"deviceData\":[]},{\"testProject\":\"projcet_szwjcjlmkt\",\"multipleId\":\"0.2992324027099942init0.4392515271129891\",\"isObtain\":true,\"deviceState\":\"开机\",\"exposureMode\":\"\",\"harnessDirection\":\"\",\"exposureProcedure\":\"\",\"tubeVoltage\":\"\",\"tubeCurrent\":\"\",\"irradiationFieldChoice\":\"\",\"irradiationFieldM1\":\"\",\"irradiationFieldM2\":\"\",\"calibrationFactor\":\"\",\"point\":[],\"testProjectId\":\"69041af5-ef38-11e9-a9b3-00163e010059\",\"testProjectType\":1,\"testProjectChineseName\":\"机房周围剂量当量率\",\"detectionLimitPieces\":\"null\",\"xcStandardName\":\"《医用X射线诊断放射防护要求》\",\"xcStandardNum\":\"GBZ 130-2013\",\"standardUseTerms\":\"7.2\",\"positionId\":\"ee503345536a864362b89af24db384d0577e\",\"deviceData\":[{\"id\":\"f03a389e-1b22-4508-b465-45301ac81ccf\",\"correctNum\":\"2019H21-20-2078835001\",\"correctTime\":\"2020-10-08 00:00:00\",\"correctUrl\":\"/upload/device/AT1121-44446 X射线场（有效期2019.10.9-2020.10.8）.pdf\",\"createtime\":\"2019-10-30 21:48:26\",\"deviceName\":\"核辐射检测仪\",\"deviceNum\":\"44446\",\"deviceUnit\":\"上海市计量测试技术研究院\",\"probeName\":null,\"probeNum\":\"1112\",\"deviceManufactor\":\"ATOMTEX\",\"type\":0,\"alpha\":null,\"beta\":null,\"deviceFactor1\":null,\"deviceFactor2\":null,\"deviceFactor3\":null,\"deviceFactor4\":null,\"deviceFactor5\":null,\"equivalentRate1\":null,\"equivalentRate2\":null,\"equivalentRate3\":null,\"equivalentRate4\":null,\"factor1\":null,\"factor2\":null,\"factor3\":null,\"factor4\":null,\"vol1\":null,\"vol2\":null,\"vol3\":null,\"vol4\":null,\"vol5\":null,\"deviceModel\":\"AT1121\",\"deviceLower\":\"0.15μSv/h\",\"lowerTime\":\"2020-10-08 00:00:00\",\"lowerUrl\":\"/upload/device/购买合同.docx\",\"subCompanyId\":\"1\",\"state\":0,\"useState\":0,\"purpose\":\"防护\",\"deviceFactor\":[{\"value\":\"80/1.07\",\"key\":1572443265583},{\"value\":\"100/1.14\",\"key\":1572443274594},{\"value\":\"150/1.09\",\"key\":1572443281894},{\"value\":\"200/1.10\",\"key\":1572443287879}],\"factor\":[{\"measure1\":\"0.007/1.1\",\"measure2\":\"\"}],\"vol\":null,\"correctNum1\":\"2019H21-20-2078835001\",\"correctTime1\":\"2020-10-08 00:00:00\",\"correctUrl1\":\"/upload/device/AT1121-44446 X射线场（有效期2019.10.9-2020.10.8）.pdf\",\"deviceFactor_gdy\":null,\"lowerUnit\":null,\"staffId\":\"c4e0be0f-b9ba-11e9-9e80-00163e010059\",\"place\":\"深圳仪器设备房\",\"metrologyRange\":null,\"accuracy\":null,\"metrologyTraceability\":null,\"testConclusion\":null,\"calibrationMethod\":\"测量值/修正值\",\"usageRequirement\":null,\"calibrationRequirements\":\"/\",\"acceptanceSituation\":\"合格\",\"acceptanceDocUrl\":\"/upload/device/验收报告.docx\",\"deviceSource\":\"购买\",\"deviceSourceUrl\":\"/upload/device/购买合同.docx\",\"isTestCalibration\":null,\"correctCalibration\":[[\"0\",\"1\"],[],[]],\"fzContainDeviceArr\":null,\"activityResponse_a\":null,\"activityResponse_b\":null,\"factor_zz\":null,\"frequency\":null,\"sysDeviceType\":0,\"testProjectId\":\"69041af5-ef38-11e9-a9b3-00163e010059\"}],\"carried\":true},{\"testProject\":\"projcet_szwjcjlmknr\",\"multipleId\":\"0.2992324027099942init0.4392515271129891\",\"isObtain\":true,\"testPoinrNum\":[true,true,true],\"testNum\":3,\"company\":\"μSv/h\",\"point\":[{\"rows\":[\"第一术者位距地面20cm（足部）\",\"\",\"\",\"\",\"\",\"\"],\"index\":1},{\"rows\":[\"第一术者位距地面80cm（下肢）\",\"\",\"\",\"\",\"\",\"\"],\"index\":2},{\"rows\":[\"第一术者位距地面105cm（腹部）\",\"\",\"\",\"\",\"\",\"\"],\"index\":3},{\"rows\":[\"第一术者位距地面125cm（胸部）\",\"\",\"\",\"\",\"\",\"\"],\"index\":4},{\"rows\":[\"第一术者位距地面155cm（头部）\",\"\",\"\",\"\",\"\",\"\"],\"index\":5},{\"rows\":[\"第二术者位距地面20cm（足部）\",\"\",\"\",\"\",\"\",\"\"],\"index\":6},{\"rows\":[\"第二术者位距地面80cm（下肢）\",\"\",\"\",\"\",\"\",\"\"],\"index\":7},{\"rows\":[\"第二术者位距地面105cm（腹部）\",\"\",\"\",\"\",\"\",\"\"],\"index\":8},{\"rows\":[\"第二术者位距地面125cm（胸部）\",\"\",\"\",\"\",\"\",\"\"],\"index\":9}],\"testProjectId\":\"69041af5-ef38-11e9-a9b3-00163e010059\",\"testProjectType\":1,\"testProjectChineseName\":\"机房周围剂量当量率\",\"detectionLimitPieces\":\"null\",\"xcStandardName\":\"《医用X射线诊断放射防护要求》\",\"xcStandardNum\":\"GBZ 130-2013\",\"standardUseTerms\":\"7.2\",\"positionId\":\"074df9a84b1e77462f8b58d8b5d64d7f0c3c\",\"deviceData\":[{\"id\":\"f03a389e-1b22-4508-b465-45301ac81ccf\",\"correctNum\":\"2019H21-20-2078835001\",\"correctTime\":\"2020-10-08 00:00:00\",\"correctUrl\":\"/upload/device/AT1121-44446 X射线场（有效期2019.10.9-2020.10.8）.pdf\",\"createtime\":\"2019-10-30 21:48:26\",\"deviceName\":\"核辐射检测仪\",\"deviceNum\":\"44446\",\"deviceUnit\":\"上海市计量测试技术研究院\",\"probeName\":null,\"probeNum\":\"1112\",\"deviceManufactor\":\"ATOMTEX\",\"type\":0,\"alpha\":null,\"beta\":null,\"deviceFactor1\":null,\"deviceFactor2\":null,\"deviceFactor3\":null,\"deviceFactor4\":null,\"deviceFactor5\":null,\"equivalentRate1\":null,\"equivalentRate2\":null,\"equivalentRate3\":null,\"equivalentRate4\":null,\"factor1\":null,\"factor2\":null,\"factor3\":null,\"factor4\":null,\"vol1\":null,\"vol2\":null,\"vol3\":null,\"vol4\":null,\"vol5\":null,\"deviceModel\":\"AT1121\",\"deviceLower\":\"0.15μSv/h\",\"lowerTime\":\"2020-10-08 00:00:00\",\"lowerUrl\":\"/upload/device/购买合同.docx\",\"subCompanyId\":\"1\",\"state\":0,\"useState\":0,\"purpose\":\"防护\",\"deviceFactor\":[{\"value\":\"80/1.07\",\"key\":1572443265583},{\"value\":\"100/1.14\",\"key\":1572443274594},{\"value\":\"150/1.09\",\"key\":1572443281894},{\"value\":\"200/1.10\",\"key\":1572443287879}],\"factor\":[{\"measure1\":\"0.007/1.1\",\"measure2\":\"\"}],\"vol\":null,\"correctNum1\":\"2019H21-20-2078835001\",\"correctTime1\":\"2020-10-08 00:00:00\",\"correctUrl1\":\"/upload/device/AT1121-44446 X射线场（有效期2019.10.9-2020.10.8）.pdf\",\"deviceFactor_gdy\":null,\"lowerUnit\":null,\"staffId\":\"c4e0be0f-b9ba-11e9-9e80-00163e010059\",\"place\":\"深圳仪器设备房\",\"metrologyRange\":null,\"accuracy\":null,\"metrologyTraceability\":null,\"testConclusion\":null,\"calibrationMethod\":\"测量值/修正值\",\"usageRequirement\":null,\"calibrationRequirements\":\"/\",\"acceptanceSituation\":\"合格\",\"acceptanceDocUrl\":\"/upload/device/验收报告.docx\",\"deviceSource\":\"购买\",\"deviceSourceUrl\":\"/upload/device/购买合同.docx\",\"isTestCalibration\":null,\"correctCalibration\":[[\"0\",\"1\"],[],[]],\"fzContainDeviceArr\":null,\"activityResponse_a\":null,\"activityResponse_b\":null,\"factor_zz\":null,\"frequency\":null,\"sysDeviceType\":0,\"testProjectId\":\"69041af5-ef38-11e9-a9b3-00163e010059\"}],\"carried\":true},{\"testProject\":\"projcet_szwjcjlmknr\",\"multipleId\":\"0.2992324027099942init0.4392515271129891\",\"isObtain\":true,\"testPoinrNum\":[true,true,true],\"testNum\":3,\"company\":\"μSv/h\",\"point\":[{\"rows\":[\"第二术者位距地面155cm（头部）\",\"\",\"\",\"\",\"\",\"\"],\"index\":10,\"multi\":true,\"multiIndex\":9},{\"rows\":[\"第三术者位距地面20cm（足部）\",\"\",\"\",\"\",\"\",\"\"],\"index\":11},{\"rows\":[\"第三术者位距地面80cm（下肢）\",\"\",\"\",\"\",\"\",\"\"],\"index\":12},{\"rows\":[\"第三术者位距地面105cm（腹部）\",\"\",\"\",\"\",\"\",\"\"],\"index\":13},{\"rows\":[\"第三术者位距地面125cm（胸部）\",\"\",\"\",\"\",\"\",\"\"],\"index\":14},{\"rows\":[\"第三术者位距地面155cm（头部）\",\"\",\"\",\"\",\"\",\"\"],\"index\":15},{\"rows\":[\"第四术者位距地面20cm（足部）\",\"\",\"\",\"\",\"\",\"\"],\"index\":16},{\"rows\":[\"第四术者位距地面80cm（下肢）\",\"\",\"\",\"\",\"\",\"\"],\"index\":17},{\"rows\":[\"第四术者位距地面105cm（腹部）\",\"\",\"\",\"\",\"\",\"\"],\"index\":18,\"multi\":true,\"multiIndex\":17},{\"rows\":[\"第四术者位距地面125cm（胸部）\",\"\",\"\",\"\",\"\",\"\"],\"index\":19},{\"rows\":[\"第四术者位距地面155cm（头部）\",\"\",\"\",\"\",\"\",\"\"],\"index\":20},{\"rows\":[\"第五术者位距地面20cm（足部）\",\"\",\"\",\"\",\"\",\"\"],\"index\":21},{\"rows\":[\"第五术者位距地面80cm（下肢）\",\"\",\"\",\"\",\"\",\"\"],\"index\":22},{\"rows\":[\"第五术者位距地面105cm（腹部）\",\"\",\"\",\"\",\"\",\"\"],\"index\":23},{\"rows\":[\"第五术者位距地面125cm（胸部）\",\"\",\"\",\"\",\"\",\"\"],\"index\":24},{\"rows\":[\"第五术者位距地面155cm（头部）\",\"\",\"\",\"\",\"\",\"\"],\"index\":25}],\"testProjectId\":\"69041af5-ef38-11e9-a9b3-00163e010059\",\"testProjectType\":1,\"testProjectChineseName\":\"机房周围剂量当量率\",\"detectionLimitPieces\":\"null\",\"xcStandardName\":\"《医用X射线诊断放射防护要求》\",\"xcStandardNum\":\"GBZ 130-2013\",\"standardUseTerms\":\"7.2\",\"positionId\":\"074df9a84b1e77462f8b58d8b5d64d7f0c3c\",\"deviceData\":[{\"id\":\"f03a389e-1b22-4508-b465-45301ac81ccf\",\"correctNum\":\"2019H21-20-2078835001\",\"correctTime\":\"2020-10-08 00:00:00\",\"correctUrl\":\"/upload/device/AT1121-44446 X射线场（有效期2019.10.9-2020.10.8）.pdf\",\"createtime\":\"2019-10-30 21:48:26\",\"deviceName\":\"核辐射检测仪\",\"deviceNum\":\"44446\",\"deviceUnit\":\"上海市计量测试技术研究院\",\"probeName\":null,\"probeNum\":\"1112\",\"deviceManufactor\":\"ATOMTEX\",\"type\":0,\"alpha\":null,\"beta\":null,\"deviceFactor1\":null,\"deviceFactor2\":null,\"deviceFactor3\":null,\"deviceFactor4\":null,\"deviceFactor5\":null,\"equivalentRate1\":null,\"equivalentRate2\":null,\"equivalentRate3\":null,\"equivalentRate4\":null,\"factor1\":null,\"factor2\":null,\"factor3\":null,\"factor4\":null,\"vol1\":null,\"vol2\":null,\"vol3\":null,\"vol4\":null,\"vol5\":null,\"deviceModel\":\"AT1121\",\"deviceLower\":\"0.15μSv/h\",\"lowerTime\":\"2020-10-08 00:00:00\",\"lowerUrl\":\"/upload/device/购买合同.docx\",\"subCompanyId\":\"1\",\"state\":0,\"useState\":0,\"purpose\":\"防护\",\"deviceFactor\":[{\"value\":\"80/1.07\",\"key\":1572443265583},{\"value\":\"100/1.14\",\"key\":1572443274594},{\"value\":\"150/1.09\",\"key\":1572443281894},{\"value\":\"200/1.10\",\"key\":1572443287879}],\"factor\":[{\"measure1\":\"0.007/1.1\",\"measure2\":\"\"}],\"vol\":null,\"correctNum1\":\"2019H21-20-2078835001\",\"correctTime1\":\"2020-10-08 00:00:00\",\"correctUrl1\":\"/upload/device/AT1121-44446 X射线场（有效期2019.10.9-2020.10.8）.pdf\",\"deviceFactor_gdy\":null,\"lowerUnit\":null,\"staffId\":\"c4e0be0f-b9ba-11e9-9e80-00163e010059\",\"place\":\"深圳仪器设备房\",\"metrologyRange\":null,\"accuracy\":null,\"metrologyTraceability\":null,\"testConclusion\":null,\"calibrationMethod\":\"测量值/修正值\",\"usageRequirement\":null,\"calibrationRequirements\":\"/\",\"acceptanceSituation\":\"合格\",\"acceptanceDocUrl\":\"/upload/device/验收报告.docx\",\"deviceSource\":\"购买\",\"deviceSourceUrl\":\"/upload/device/购买合同.docx\",\"isTestCalibration\":null,\"correctCalibration\":[[\"0\",\"1\"],[],[]],\"fzContainDeviceArr\":null,\"activityResponse_a\":null,\"activityResponse_b\":null,\"factor_zz\":null,\"frequency\":null,\"sysDeviceType\":0,\"testProjectId\":\"69041af5-ef38-11e9-a9b3-00163e010059\"}],\"carried\":true},{\"testProject\":\"project_ts_tssjzrstbkqbsdnldxz1\",\"correct\":\"透视受检者入射体表空气比释动能率典型值\",\"pointId\":\"0acabc224fdced452ef9fc4ca828e58fe50e\",\"foreverId\":\"b5d16e42fcbb3c49e2297905feb666c3fd4a\",\"sizeJudge\":0,\"multipleId\":\"0.3607852071217288init0.8155375905627111\",\"point\":[],\"size\":\"\",\"deviceType\":\"\",\"testProjectId\":\"fabac3dd-6b1d-11ea-831a-00163e067057\",\"testProjectType\":1,\"testProjectChineseName\":\"透视-透视受检者入射体表空气比释动能率典型值\",\"xcStandardName\":\"《医用常规X射线诊断设备质量控制检测规范》\",\"xcStandardNum\":\"WS 76-2017\",\"standardUseTerms\":\"（7.1）\",\"positionId\":\"b15e639d7205e14774482cc058748b9e6968\",\"deviceData\":[],\"carried\":true},{\"testProject\":\"project_ts_tssjzrstbkqbsdnldxz2\",\"correct\":\"透视受检者入射体表空气比释动能率典型值\",\"pointId\":\"efb91b0840e9cf440028417b2d84ac6b1a5d\",\"foreverId\":\"137a61703433bd46532884f5e5a0389c96d0\",\"multipleId\":\"0.5699192422853605init0.02436367008654594\",\"company\":\"\",\"sizeList\":\"\",\"factorArr\":[{\"value\":\"60/1.042\",\"key\":1578563471520},{\"value\":\"70/1.035\",\"key\":1578563499551},{\"value\":\"80/1.007\",\"key\":1578563507402},{\"value\":\"100/0.997\",\"key\":1578563521640},{\"value\":\"135/1.008\",\"key\":1578563550151}],\"point\":[{\"view\":\"\",\"voltage\":\"\",\"electricCurrent\":\"\",\"val1\":\"\",\"val2\":\"\",\"val3\":\"\",\"factor\":\"\",\"result\":\"\",\"isPrototype\":true,\"index\":1}],\"testProjectId\":\"fabac3dd-6b1d-11ea-831a-00163e067057\",\"testProjectType\":1,\"testProjectChineseName\":\"透视-透视受检者入射体表空气比释动能率典型值\",\"xcStandardName\":\"《医用常规X射线诊断设备质量控制检测规范》\",\"xcStandardNum\":\"WS 76-2017\",\"standardUseTerms\":\"（7.1）\",\"positionId\":\"907a06fefd539141d169819a5118a8e5690c\",\"deviceData\":[],\"carried\":true},{\"testProject\":\"project_ts_tssjzrstbkqbsdnlzdz1\",\"correct\":\"透视受检者入射体表空气比释动能率最大值\",\"pointId\":\"2c8a5d3a0cbfcd4fe2d96cb7d57aeba9d88b\",\"foreverId\":\"db1502e70f6d3f4d5db8bc0d73293fd833fc\",\"sizeJudge\":0,\"multipleId\":\"0.6088712271380192init0.7971159601252884\",\"point\":[],\"size\":\"\",\"deviceType\":\"\",\"testProjectId\":\"100e50c6-6b1e-11ea-831a-00163e067057\",\"testProjectType\":1,\"testProjectChineseName\":\"透视-透视受检者入射体表空气比释动能率最大值\",\"xcStandardName\":\"《医用常规X射线诊断设备质量控制检测规范》\",\"xcStandardNum\":\"WS 76-2017\",\"standardUseTerms\":\"（7.2）\",\"positionId\":\"c56eee9496c9c444d199521a99d08541f927\",\"deviceData\":[{\"id\":\"41419363-1128-4bb3-94a0-6dfc5bf6b8f2\",\"correctNum\":null,\"correctTime\":\"2020-07-27 08:00:00\",\"correctUrl\":null,\"createtime\":\"2020-04-28 13:53:23\",\"deviceName\":\"湘亭实验室测试设备\",\"deviceNum\":\"XT006\",\"deviceUnit\":null,\"probeName\":null,\"probeNum\":null,\"deviceManufactor\":\"杭州湘亭科技有限公司\",\"type\":0,\"alpha\":null,\"beta\":null,\"deviceFactor1\":null,\"deviceFactor2\":null,\"deviceFactor3\":null,\"deviceFactor4\":null,\"deviceFactor5\":null,\"equivalentRate1\":null,\"equivalentRate2\":null,\"equivalentRate3\":null,\"equivalentRate4\":null,\"factor1\":null,\"factor2\":null,\"factor3\":null,\"factor4\":null,\"vol1\":null,\"vol2\":null,\"vol3\":null,\"vol4\":null,\"vol5\":null,\"deviceModel\":\"XT\",\"deviceLower\":\"\",\"lowerTime\":null,\"lowerUrl\":null,\"subCompanyId\":\"1\",\"state\":0,\"useState\":0,\"purpose\":\"实验室\",\"deviceFactor\":null,\"factor\":null,\"vol\":null,\"correctNum1\":null,\"correctTime1\":null,\"correctUrl1\":null,\"deviceFactor_gdy\":null,\"lowerUnit\":null,\"staffId\":null,\"place\":null,\"metrologyRange\":null,\"accuracy\":null,\"metrologyTraceability\":null,\"testConclusion\":null,\"calibrationMethod\":null,\"usageRequirement\":null,\"calibrationRequirements\":\"1\",\"acceptanceSituation\":\"合格\",\"acceptanceDocUrl\":null,\"deviceSource\":\"购买\",\"deviceSourceUrl\":null,\"isTestCalibration\":null,\"correctCalibration\":null,\"fzContainDeviceArr\":null,\"activityResponse_a\":null,\"activityResponse_b\":null,\"factor_zz\":null,\"frequency\":null,\"sysDeviceType\":0,\"testProjectId\":\"100e50c6-6b1e-11ea-831a-00163e067057\"},{\"id\":\"a1ae7fd3-84eb-4a17-bcc3-9879f5e16341\",\"correctNum\":\"2019H21-20-2078835001\",\"correctTime\":\"2020-10-08 00:00:00\",\"correctUrl\":\"/upload/device/AT1121-44446 X射线场（有效期2019.10.9-2020.10.8）.pdf\",\"createtime\":\"2020-01-10 18:21:10\",\"deviceName\":\"核辐射检测仪\",\"deviceNum\":\"44446（杭州防护）\",\"deviceUnit\":\"上海市计量测试计量研究院\",\"probeName\":null,\"probeNum\":null,\"deviceManufactor\":\"ATOMTEX\",\"type\":0,\"alpha\":null,\"beta\":null,\"deviceFactor1\":null,\"deviceFactor2\":null,\"deviceFactor3\":null,\"deviceFactor4\":null,\"deviceFactor5\":null,\"equivalentRate1\":null,\"equivalentRate2\":null,\"equivalentRate3\":null,\"equivalentRate4\":null,\"factor1\":null,\"factor2\":null,\"factor3\":null,\"factor4\":null,\"vol1\":null,\"vol2\":null,\"vol3\":null,\"vol4\":null,\"vol5\":null,\"deviceModel\":\"AT1121\",\"deviceLower\":\"0.15μsv/h\",\"lowerTime\":\"2020-01-09 00:00:00\",\"lowerUrl\":\"/upload/device/购买合同.docx\",\"subCompanyId\":\"1\",\"state\":0,\"useState\":0,\"purpose\":\"防护\",\"deviceFactor\":[{\"value\":\"80/1.07\",\"key\":1578563014366},{\"value\":\"100/1.14\",\"key\":1578563102648},{\"value\":\"150/1.09\",\"key\":1578563125335},{\"value\":\"200/1.10\",\"key\":1578563133301}],\"factor\":[{\"measure1\":\"1.10\",\"measure2\":\"\"}],\"vol\":null,\"correctNum1\":\"2019H21-20-2078835001\",\"correctTime1\":\"2020-10-08 00:00:00\",\"correctUrl1\":\"/upload/device/AT1121-44446 X射线场（有效期2019.10.9-2020.10.8）.pdf\",\"deviceFactor_gdy\":null,\"lowerUnit\":null,\"staffId\":\"c4e0be0f-b9ba-11e9-9e80-00163e010059\",\"place\":\"深圳仪器设备间\",\"metrologyRange\":null,\"accuracy\":null,\"metrologyTraceability\":null,\"testConclusion\":null,\"calibrationMethod\":\"\",\"usageRequirement\":null,\"calibrationRequirements\":\"/\",\"acceptanceSituation\":\"合格\",\"acceptanceDocUrl\":\"/upload/device/验收报告.docx\",\"deviceSource\":\"购买\",\"deviceSourceUrl\":\"/upload/device/购买合同.docx\",\"isTestCalibration\":null,\"correctCalibration\":[[\"0\",\"1\"],[],[]],\"fzContainDeviceArr\":null,\"activityResponse_a\":null,\"activityResponse_b\":null,\"factor_zz\":null,\"frequency\":null,\"sysDeviceType\":0,\"testProjectId\":\"100e50c6-6b1e-11ea-831a-00163e067057\"}],\"carried\":true},{\"testProject\":\"project_ts_tssjzrstbkqbsdnlzdz2\",\"correct\":\"透视受检者入射体表空气比释动能率最大值\",\"pointId\":\"77d54b2ba69118426ee807fa23ad89b134c7\",\"foreverId\":\"7520474b68c6b649cefabd7b1e8e6f9e5458\",\"multipleId\":\"0.5900045339286981init0.1377297007842233\",\"company\":\"\",\"sizeList\":\"\",\"factorArr\":[{\"value\":\"60/1.042\",\"key\":1578563471520},{\"value\":\"70/1.035\",\"key\":1578563499551},{\"value\":\"80/1.007\",\"key\":1578563507402},{\"value\":\"100/0.997\",\"key\":1578563521640},{\"value\":\"135/1.008\",\"key\":1578563550151}],\"point\":[{\"view\":\"\",\"voltage\":\"\",\"electricCurrent\":\"\",\"val1\":\"\",\"val2\":\"\",\"val3\":\"\",\"factor\":\"\",\"result\":\"\",\"isPrototype\":true,\"index\":1}],\"testProjectId\":\"100e50c6-6b1e-11ea-831a-00163e067057\",\"testProjectType\":1,\"testProjectChineseName\":\"透视-透视受检者入射体表空气比释动能率最大值\",\"xcStandardName\":\"《医用常规X射线诊断设备质量控制检测规范》\",\"xcStandardNum\":\"WS 76-2017\",\"standardUseTerms\":\"（7.2）\",\"positionId\":\"d4749f77361d9043f698d98c5ec85f7fa204\",\"deviceData\":[{\"id\":\"41419363-1128-4bb3-94a0-6dfc5bf6b8f2\",\"correctNum\":null,\"correctTime\":\"2020-07-27 08:00:00\",\"correctUrl\":null,\"createtime\":\"2020-04-28 13:53:23\",\"deviceName\":\"湘亭实验室测试设备\",\"deviceNum\":\"XT006\",\"deviceUnit\":null,\"probeName\":null,\"probeNum\":null,\"deviceManufactor\":\"杭州湘亭科技有限公司\",\"type\":0,\"alpha\":null,\"beta\":null,\"deviceFactor1\":null,\"deviceFactor2\":null,\"deviceFactor3\":null,\"deviceFactor4\":null,\"deviceFactor5\":null,\"equivalentRate1\":null,\"equivalentRate2\":null,\"equivalentRate3\":null,\"equivalentRate4\":null,\"factor1\":null,\"factor2\":null,\"factor3\":null,\"factor4\":null,\"vol1\":null,\"vol2\":null,\"vol3\":null,\"vol4\":null,\"vol5\":null,\"deviceModel\":\"XT\",\"deviceLower\":\"\",\"lowerTime\":null,\"lowerUrl\":null,\"subCompanyId\":\"1\",\"state\":0,\"useState\":0,\"purpose\":\"实验室\",\"deviceFactor\":null,\"factor\":null,\"vol\":null,\"correctNum1\":null,\"correctTime1\":null,\"correctUrl1\":null,\"deviceFactor_gdy\":null,\"lowerUnit\":null,\"staffId\":null,\"place\":null,\"metrologyRange\":null,\"accuracy\":null,\"metrologyTraceability\":null,\"testConclusion\":null,\"calibrationMethod\":null,\"usageRequirement\":null,\"calibrationRequirements\":\"1\",\"acceptanceSituation\":\"合格\",\"acceptanceDocUrl\":null,\"deviceSource\":\"购买\",\"deviceSourceUrl\":null,\"isTestCalibration\":null,\"correctCalibration\":null,\"fzContainDeviceArr\":null,\"activityResponse_a\":null,\"activityResponse_b\":null,\"factor_zz\":null,\"frequency\":null,\"sysDeviceType\":0,\"testProjectId\":\"100e50c6-6b1e-11ea-831a-00163e067057\"},{\"id\":\"a1ae7fd3-84eb-4a17-bcc3-9879f5e16341\",\"correctNum\":\"2019H21-20-2078835001\",\"correctTime\":\"2020-10-08 00:00:00\",\"correctUrl\":\"/upload/device/AT1121-44446 X射线场（有效期2019.10.9-2020.10.8）.pdf\",\"createtime\":\"2020-01-10 18:21:10\",\"deviceName\":\"核辐射检测仪\",\"deviceNum\":\"44446（杭州防护）\",\"deviceUnit\":\"上海市计量测试计量研究院\",\"probeName\":null,\"probeNum\":null,\"deviceManufactor\":\"ATOMTEX\",\"type\":0,\"alpha\":null,\"beta\":null,\"deviceFactor1\":null,\"deviceFactor2\":null,\"deviceFactor3\":null,\"deviceFactor4\":null,\"deviceFactor5\":null,\"equivalentRate1\":null,\"equivalentRate2\":null,\"equivalentRate3\":null,\"equivalentRate4\":null,\"factor1\":null,\"factor2\":null,\"factor3\":null,\"factor4\":null,\"vol1\":null,\"vol2\":null,\"vol3\":null,\"vol4\":null,\"vol5\":null,\"deviceModel\":\"AT1121\",\"deviceLower\":\"0.15μsv/h\",\"lowerTime\":\"2020-01-09 00:00:00\",\"lowerUrl\":\"/upload/device/购买合同.docx\",\"subCompanyId\":\"1\",\"state\":0,\"useState\":0,\"purpose\":\"防护\",\"deviceFactor\":[{\"value\":\"80/1.07\",\"key\":1578563014366},{\"value\":\"100/1.14\",\"key\":1578563102648},{\"value\":\"150/1.09\",\"key\":1578563125335},{\"value\":\"200/1.10\",\"key\":1578563133301}],\"factor\":[{\"measure1\":\"1.10\",\"measure2\":\"\"}],\"vol\":null,\"correctNum1\":\"2019H21-20-2078835001\",\"correctTime1\":\"2020-10-08 00:00:00\",\"correctUrl1\":\"/upload/device/AT1121-44446 X射线场（有效期2019.10.9-2020.10.8）.pdf\",\"deviceFactor_gdy\":null,\"lowerUnit\":null,\"staffId\":\"c4e0be0f-b9ba-11e9-9e80-00163e010059\",\"place\":\"深圳仪器设备间\",\"metrologyRange\":null,\"accuracy\":null,\"metrologyTraceability\":null,\"testConclusion\":null,\"calibrationMethod\":\"\",\"usageRequirement\":null,\"calibrationRequirements\":\"/\",\"acceptanceSituation\":\"合格\",\"acceptanceDocUrl\":\"/upload/device/验收报告.docx\",\"deviceSource\":\"购买\",\"deviceSourceUrl\":\"/upload/device/购买合同.docx\",\"isTestCalibration\":null,\"correctCalibration\":[[\"0\",\"1\"],[],[]],\"fzContainDeviceArr\":null,\"activityResponse_a\":null,\"activityResponse_b\":null,\"factor_zz\":null,\"frequency\":null,\"sysDeviceType\":0,\"testProjectId\":\"100e50c6-6b1e-11ea-831a-00163e067057\"}],\"carried\":true},{\"testProject\":\"project_ts_tsygplmd1\",\"correct\":\"透视荧光屏灵敏度\",\"pointId\":\"1fe02f05c350244960090b43e169ecfda2ce\",\"foreverId\":\"fd02990d0dc78845d988363e16888c3c9109\",\"multipleId\":\"0.9205087870048336init0.5986990116653361\",\"point\":[],\"testProjectId\":\"2421cb45-6b1e-11ea-831a-00163e067057\",\"testProjectType\":1,\"testProjectChineseName\":\"透视-透视荧光屏灵敏度\",\"xcStandardName\":\"《医用常规X射线诊断设备质量控制检测规范》\",\"xcStandardNum\":\"WS 76-2017\",\"standardUseTerms\":\"（7.3）\",\"positionId\":\"b038aa5a3360694df9b8418ff9dd068d06d9\",\"deviceData\":[],\"carried\":true},{\"testProject\":\"project_ts_tsygplmd2\",\"correct\":\"透视荧光屏灵敏度\",\"pointId\":\"7d5c17873947da4340b881b5eb586d1d382b\",\"foreverId\":\"ac6250cebe3e3749eb6872e7c9c124291ba9\",\"multipleId\":\"0.40013314250468124init0.33292492202889656\",\"factorArr\":[{\"value\":\"60/1.042\",\"key\":1578563471520},{\"value\":\"70/1.035\",\"key\":1578563499551},{\"value\":\"80/1.007\",\"key\":1578563507402},{\"value\":\"100/0.997\",\"key\":1578563521640},{\"value\":\"135/1.008\",\"key\":1578563550151}],\"point\":[{\"voltage\":\"\",\"electricCurrent\":\"\",\"K\":\"\",\"b\":\"\",\"factor\":\"\",\"result\":\"\",\"isPrototype\":true,\"index\":1}],\"testProjectId\":\"2421cb45-6b1e-11ea-831a-00163e067057\",\"testProjectType\":1,\"testProjectChineseName\":\"透视-透视荧光屏灵敏度\",\"xcStandardName\":\"《医用常规X射线诊断设备质量控制检测规范》\",\"xcStandardNum\":\"WS 76-2017\",\"standardUseTerms\":\"（7.3）\",\"positionId\":\"cb5f4b884e6a544f8e59a0d15fe52f691a43\",\"deviceData\":[],\"carried\":true},{\"testProject\":\"projcet_ts_kjfbl1\",\"correct\":\"空间分辨力\",\"pointId\":\"d24524dc66ff924fd5f88e9fd8ef02387c9d\",\"foreverId\":\"bad686f48c5fdd4ba8d8a5ccc5a92aad5a7b\",\"multipleId\":\"0.47152013832233153init0.07781735794235778\",\"point\":[],\"testProjectId\":\"37cd3a5a-6b1e-11ea-831a-00163e067057\",\"testProjectType\":1,\"testProjectChineseName\":\"透视-空间分辨力\",\"xcStandardName\":\"《医用常规X射线诊断设备质量控制检测规范》\",\"xcStandardNum\":\"WS 76-2017\",\"standardUseTerms\":\"（7.5）\",\"positionId\":\"088defaffa92ec43435868a782f3072bca15\",\"deviceData\":[{\"id\":\"1f0e69c3-8ca5-4b1d-9f41-e51aa0ac3d27\",\"correctNum\":\"2019H00-10-2208576001\",\"correctTime\":\"2020-12-09 00:00:00\",\"correctUrl\":\"/upload/device/RF探头有效期：2019.12.3-2020.12.2.pdf\",\"createtime\":\"2020-01-10 19:42:24\",\"deviceName\":\"X射线机质控检测仪\",\"deviceNum\":\"209590（杭州性能）\",\"deviceUnit\":\"上海市计量测试技术研究院\",\"probeName\":\"摄影/透视探头\",\"probeNum\":\"261035\",\"deviceManufactor\":\"Unfors RaySafe\",\"type\":0,\"alpha\":null,\"beta\":null,\"deviceFactor1\":null,\"deviceFactor2\":null,\"deviceFactor3\":null,\"deviceFactor4\":null,\"deviceFactor5\":null,\"equivalentRate1\":null,\"equivalentRate2\":null,\"equivalentRate3\":null,\"equivalentRate4\":null,\"factor1\":null,\"factor2\":null,\"factor3\":null,\"factor4\":null,\"vol1\":null,\"vol2\":null,\"vol3\":null,\"vol4\":null,\"vol5\":null,\"deviceModel\":\"X2\",\"deviceLower\":\"\",\"lowerTime\":null,\"lowerUrl\":null,\"subCompanyId\":\"1\",\"state\":0,\"useState\":0,\"purpose\":\"性能\",\"deviceFactor\":[{\"value\":\"60/1.042\",\"key\":1578563471520},{\"value\":\"70/1.035\",\"key\":1578563499551},{\"value\":\"80/1.007\",\"key\":1578563507402},{\"value\":\"100/0.997\",\"key\":1578563521640},{\"value\":\"135/1.008\",\"key\":1578563550151}],\"factor\":null,\"vol\":null,\"correctNum1\":\"2019H00-10-2208576001\",\"correctTime1\":\"2020-12-09 00:00:00\",\"correctUrl1\":\"/upload/device/RF探头有效期：2019.12.3-2020.12.2.pdf\",\"deviceFactor_gdy\":[{\"value\":\"39.7/1.0075567\",\"key\":1578563575402},{\"value\":\"50/1\",\"key\":1578563613087},{\"value\":\"60.5/1.0049587\",\"key\":1578563621854},{\"value\":\"70.3/1.009957326\",\"key\":1578563622997},{\"value\":\"80.6/1.004962779\",\"key\":1578563623937},{\"value\":\"90.90/0.99889989\",\"key\":1578563624754},{\"value\":\"101.10 /0.99901088\",\"key\":1578563690850},{\"value\":\"111.20/0.997302158\",\"key\":1578563712633},{\"value\":\"121.50 /0.995884774\",\"key\":1578563743086}],\"lowerUnit\":null,\"staffId\":\"c4e0be0f-b9ba-11e9-9e80-00163e010059\",\"place\":\"深圳仪器设备房\",\"metrologyRange\":null,\"accuracy\":null,\"metrologyTraceability\":null,\"testConclusion\":null,\"calibrationMethod\":null,\"usageRequirement\":null,\"calibrationRequirements\":\"\",\"acceptanceSituation\":\"合格\",\"acceptanceDocUrl\":\"/upload/device/购买合同.docx\",\"deviceSource\":\"购买\",\"deviceSourceUrl\":\"/upload/device/购买合同.docx\",\"isTestCalibration\":null,\"correctCalibration\":[0,1],\"fzContainDeviceArr\":null,\"activityResponse_a\":null,\"activityResponse_b\":null,\"factor_zz\":null,\"frequency\":null,\"sysDeviceType\":0,\"testProjectId\":\"37cd3a5a-6b1e-11ea-831a-00163e067057\"}],\"carried\":true},{\"testProject\":\"projcet_ts_kjfbl2\",\"correct\":\"空间分辨力\",\"pointId\":\"aa9042242ad96f428f7893e4b07042dd466e\",\"foreverId\":\"480de0f3308ec74e300829192cb5612c9be1\",\"multipleId\":\"0.6303308950795494init0.9140532441846771\",\"sizeList\":\"\",\"point\":[{\"view\":\"\",\"voltage\":\"\",\"electricCurrent\":\"\",\"result\":\"\",\"isPrototype\":true,\"index\":1}],\"testProjectId\":\"37cd3a5a-6b1e-11ea-831a-00163e067057\",\"testProjectType\":1,\"testProjectChineseName\":\"透视-空间分辨力\",\"xcStandardName\":\"《医用常规X射线诊断设备质量控制检测规范》\",\"xcStandardNum\":\"WS 76-2017\",\"standardUseTerms\":\"（7.5）\",\"positionId\":\"38666e0720c55344aaeaeae2729d5a140057\",\"deviceData\":[{\"id\":\"1f0e69c3-8ca5-4b1d-9f41-e51aa0ac3d27\",\"correctNum\":\"2019H00-10-2208576001\",\"correctTime\":\"2020-12-09 00:00:00\",\"correctUrl\":\"/upload/device/RF探头有效期：2019.12.3-2020.12.2.pdf\",\"createtime\":\"2020-01-10 19:42:24\",\"deviceName\":\"X射线机质控检测仪\",\"deviceNum\":\"209590（杭州性能）\",\"deviceUnit\":\"上海市计量测试技术研究院\",\"probeName\":\"摄影/透视探头\",\"probeNum\":\"261035\",\"deviceManufactor\":\"Unfors RaySafe\",\"type\":0,\"alpha\":null,\"beta\":null,\"deviceFactor1\":null,\"deviceFactor2\":null,\"deviceFactor3\":null,\"deviceFactor4\":null,\"deviceFactor5\":null,\"equivalentRate1\":null,\"equivalentRate2\":null,\"equivalentRate3\":null,\"equivalentRate4\":null,\"factor1\":null,\"factor2\":null,\"factor3\":null,\"factor4\":null,\"vol1\":null,\"vol2\":null,\"vol3\":null,\"vol4\":null,\"vol5\":null,\"deviceModel\":\"X2\",\"deviceLower\":\"\",\"lowerTime\":null,\"lowerUrl\":null,\"subCompanyId\":\"1\",\"state\":0,\"useState\":0,\"purpose\":\"性能\",\"deviceFactor\":[{\"value\":\"60/1.042\",\"key\":1578563471520},{\"value\":\"70/1.035\",\"key\":1578563499551},{\"value\":\"80/1.007\",\"key\":1578563507402},{\"value\":\"100/0.997\",\"key\":1578563521640},{\"value\":\"135/1.008\",\"key\":1578563550151}],\"factor\":null,\"vol\":null,\"correctNum1\":\"2019H00-10-2208576001\",\"correctTime1\":\"2020-12-09 00:00:00\",\"correctUrl1\":\"/upload/device/RF探头有效期：2019.12.3-2020.12.2.pdf\",\"deviceFactor_gdy\":[{\"value\":\"39.7/1.0075567\",\"key\":1578563575402},{\"value\":\"50/1\",\"key\":1578563613087},{\"value\":\"60.5/1.0049587\",\"key\":1578563621854},{\"value\":\"70.3/1.009957326\",\"key\":1578563622997},{\"value\":\"80.6/1.004962779\",\"key\":1578563623937},{\"value\":\"90.90/0.99889989\",\"key\":1578563624754},{\"value\":\"101.10 /0.99901088\",\"key\":1578563690850},{\"value\":\"111.20/0.997302158\",\"key\":1578563712633},{\"value\":\"121.50 /0.995884774\",\"key\":1578563743086}],\"lowerUnit\":null,\"staffId\":\"c4e0be0f-b9ba-11e9-9e80-00163e010059\",\"place\":\"深圳仪器设备房\",\"metrologyRange\":null,\"accuracy\":null,\"metrologyTraceability\":null,\"testConclusion\":null,\"calibrationMethod\":null,\"usageRequirement\":null,\"calibrationRequirements\":\"\",\"acceptanceSituation\":\"合格\",\"acceptanceDocUrl\":\"/upload/device/购买合同.docx\",\"deviceSource\":\"购买\",\"deviceSourceUrl\":\"/upload/device/购买合同.docx\",\"isTestCalibration\":null,\"correctCalibration\":[0,1],\"fzContainDeviceArr\":null,\"activityResponse_a\":null,\"activityResponse_b\":null,\"factor_zz\":null,\"frequency\":null,\"sysDeviceType\":0,\"testProjectId\":\"37cd3a5a-6b1e-11ea-831a-00163e067057\"}],\"carried\":true},{\"testProject\":\"project_ts_ddbfbl1\",\"correct\":\"低对比分辨力\",\"pointId\":\"cd9db7cc1a10af475bda3ff8ef242fc8766a\",\"foreverId\":\"cf4fe14f57230540a61a16ce46cea4753111\",\"multipleId\":\"0.21179777318773807init0.048252442671909535\",\"point\":[],\"testProjectId\":\"49782881-6b1e-11ea-831a-00163e067057\",\"testProjectType\":1,\"testProjectChineseName\":\"透视-低对比分辨力\",\"xcStandardName\":\"《医用常规X射线诊断设备质量控制检测规范》\",\"xcStandardNum\":\"WS 76-2017\",\"standardUseTerms\":\"（7.5）\",\"positionId\":\"d46bde6be084154048183c592ba5183be471\",\"deviceData\":[],\"carried\":true},{\"testProject\":\"project_ts_ddbfbl2\",\"correct\":\"低对比分辨力\",\"pointId\":\"c60d478c3884c24f25fa2689e4520857d7a4\",\"foreverId\":\"9adb73608674a94dbc38cea77b09698c19cd\",\"multipleId\":\"0.5611682784701841init0.8657646618384949\",\"sizeList\":\"\",\"point\":[{\"view\":\"\",\"voltage\":\"\",\"electricCurrent\":\"\",\"num\":\"\",\"result1\":\"\",\"result2\":\"\",\"isPrototype\":true,\"index\":1}],\"testProjectId\":\"49782881-6b1e-11ea-831a-00163e067057\",\"testProjectType\":1,\"testProjectChineseName\":\"透视-低对比分辨力\",\"xcStandardName\":\"《医用常规X射线诊断设备质量控制检测规范》\",\"xcStandardNum\":\"WS 76-2017\",\"standardUseTerms\":\"（7.5）\",\"positionId\":\"06d98c050cfc9d45689855c269350d4273ea\",\"deviceData\":[],\"carried\":true},{\"testProject\":\"project_ts_yxjsqrspqkqbsdnl1\",\"correct\":\"影像接收器入射屏前空气比释动能率\",\"pointId\":\"91cc63ac223bb047b9a9861bc12c61accc9d\",\"foreverId\":\"95a06ec9331b9d4b96b844bf6f24020a8d91\",\"multipleId\":\"0.817513288586027init0.4369700416992772\",\"point\":[],\"size\":\"\",\"deviceType\":\"\",\"testProjectId\":\"5b0e081f-6b1e-11ea-831a-00163e067057\",\"testProjectType\":1,\"testProjectChineseName\":\"透视-影像接收器入射屏前空气比释动能率\",\"xcStandardName\":\"《医用常规X射线诊断设备质量控制检测规范》\",\"xcStandardNum\":\"WS 76-2017\",\"standardUseTerms\":\"（7.6）\",\"positionId\":\"2632c6ca62226749cf68dffa7f4831523f17\",\"deviceData\":[],\"carried\":true},{\"testProject\":\"project_ts_yxjsqrspqkqbsdnl2\",\"correct\":\"影像接收器入射屏前空气比释动能率\",\"pointId\":\"ea1a7c031c5d5344c8da81fec9bf15439bcc\",\"foreverId\":\"3a3d37d4eefb9a4d30b84cc4ac46b64b7d8c\",\"multipleId\":\"0.9356847187093407init0.0065365442868414725\",\"company\":\"\",\"sizeList\":\"\",\"factorArr\":[{\"value\":\"60/1.042\",\"key\":1578563471520},{\"value\":\"70/1.035\",\"key\":1578563499551},{\"value\":\"80/1.007\",\"key\":1578563507402},{\"value\":\"100/0.997\",\"key\":1578563521640},{\"value\":\"135/1.008\",\"key\":1578563550151}],\"point\":[{\"view\":\"\",\"voltage\":\"\",\"electricCurrent\":\"\",\"val1\":\"\",\"val2\":\"\",\"val3\":\"\",\"factor\":\"\",\"filterLine\":\"\",\"result\":\"\",\"isPrototype\":true,\"index\":1}],\"testProjectId\":\"5b0e081f-6b1e-11ea-831a-00163e067057\",\"testProjectType\":1,\"testProjectChineseName\":\"透视-影像接收器入射屏前空气比释动能率\",\"xcStandardName\":\"《医用常规X射线诊断设备质量控制检测规范》\",\"xcStandardNum\":\"WS 76-2017\",\"standardUseTerms\":\"（7.6）\",\"positionId\":\"c0071cae76d17149aac946af04554cc097d3\",\"deviceData\":[],\"carried\":true},{\"testProject\":\"project_ts_zdldkz1\",\"correct\":\"自动亮度控制\",\"pointId\":\"d4b214ae0f7d084a7a59056167504c51c703\",\"foreverId\":\"31c6e64380c5c94aa6984507c6b30ed2a333\",\"multipleId\":\"0.37864000294135036init0.41112673677939915\",\"point\":[],\"testProjectId\":\"6d24a4ac-6b1e-11ea-831a-00163e067057\",\"testProjectType\":1,\"testProjectChineseName\":\"透视-自动亮度控制\",\"xcStandardName\":\"《医用常规X射线诊断设备质量控制检测规范》\",\"xcStandardNum\":\"WS 76-2017\",\"standardUseTerms\":\"（7.7）\",\"positionId\":\"29f87ec37ef86c4b0a49313feb382e3817fb\",\"deviceData\":[],\"carried\":true},{\"testProject\":\"project_ts_zdldkz2\",\"correct\":\"自动亮度控制\",\"pointId\":\"90e7726a22645d43a878b0b52c337ae3416c\",\"foreverId\":\"0471771937bb1c4968497a1ac24b17330343\",\"multipleId\":\"0.18267883690186926init0.638374792686963\",\"radio\":\"\",\"point\":[{\"testingConditions\":\"20mmAl\",\"val1\":\"\",\"val2\":\"\",\"val3\":\"\",\"val4\":\"\",\"val5\":\"\",\"val6\":\"\",\"isPrototype\":true,\"index\":1},{\"testingConditions\":\"20mmAl+1.5mmCu\",\"val1\":\"\",\"val2\":\"\",\"val3\":\"\",\"val4\":\"\",\"val5\":\"\",\"val6\":\"\",\"isPrototype\":true,\"index\":2},{\"testingConditions\":\"亮度变化率/%\",\"val1\":\"\",\"val2\":\"\",\"val3\":\"\",\"val4\":\"\",\"val5\":\"\",\"val6\":\"\",\"isPrototype\":true,\"index\":3}],\"testProjectId\":\"6d24a4ac-6b1e-11ea-831a-00163e067057\",\"testProjectType\":1,\"testProjectChineseName\":\"透视-自动亮度控制\",\"xcStandardName\":\"《医用常规X射线诊断设备质量控制检测规范》\",\"xcStandardNum\":\"WS 76-2017\",\"standardUseTerms\":\"（7.7）\",\"positionId\":\"5d0a02fd303ed94f8ff8b243c4caf49c40a4\",\"deviceData\":[],\"carried\":true},{\"testProject\":\"project_ts_zsyyyxjsqzxpc\",\"correct\":\"照射野与影像接收器中心偏差\",\"pointId\":\"a6d199db3d86e34753882180d7926fbf9e7a\",\"foreverId\":\"067c3e783d48ce440c88554e381154c7682c\",\"multipleId\":\"0.8269715747385629init0.050491748475578024\",\"point\":[],\"view\":\"\",\"SID\":\"\",\"deviation\":\"\",\"testProjectId\":\"83148145-6b1e-11ea-831a-00163e067057\",\"testProjectType\":1,\"testProjectChineseName\":\"透视-照射野与影像接收器中心偏差\",\"xcStandardName\":\"《医用常规X射线诊断设备质量控制检测规范》\",\"xcStandardNum\":\"WS 76-2017\",\"standardUseTerms\":\"（7.8）\",\"positionId\":\"c70aeaa5b14c9e43b2587df3f1e67cf97778\",\"deviceData\":[],\"carried\":true},{\"testProject\":\"project_ts_zdzsyyptygccxtsdhpj\",\"correct\":\"最大照射野与普通荧光屏尺寸相同时的台屏距\",\"pointId\":\"507ca57e93562f4fa5c8b5cf1c9f75d0605b\",\"foreverId\":\"b08bfadab60f004ebdc957602c0837987531\",\"multipleId\":\"0.1923509754213355init0.6387751839760438\",\"point\":[],\"distance\":\"\",\"testProjectId\":\"97635d6e-6b1e-11ea-831a-00163e067057\",\"testProjectType\":1,\"testProjectChineseName\":\"透视-最大照射野与普通荧光屏尺寸相同时的台屏距\",\"xcStandardName\":\"《医用常规X射线诊断设备质量控制检测规范》\",\"xcStandardNum\":\"WS 76-2017\",\"standardUseTerms\":\"（1.0）\",\"positionId\":\"e85242fbdfaa294548c80c0438f0dc915f3a\",\"deviceData\":[],\"carried\":true},{\"testProject\":\"project_deleteReason\",\"testProjectChineseName\":\"删除原因\",\"point\":[],\"multipleId\":\"0.784149450259755init0.01520018692256242\",\"positionId\":\"6b2d2069ce3e4c4ad62980cf913b65aca243\",\"testProjectId\":\"0.400808349173656260.9837506630569341\",\"deviceData\":[],\"carried\":true}]","docNum":"","docPass":0,"docTime":null,"docUrl":null,"expectTime":"","humidity":0,"inserttime":null,"isDeviate":0,"isDone":1,"isSend":1,"isAccept":2,"isMaterial":0,"isCheckUnit":0,"isToSys":0,"isReturn":0,"returnReason":null,"latLngType":"","lat":30.4247,"lng":120.307,"location":"","measureDataPdfUrl":null,"measureDataUrl":null,"monitorType":"","needTime":"2020-06-29 22:45:25","lastNeedTime":"无","nominalCapacity":"1","nominalCapacity1":"1","note":"","samplePass":4,"other":"","pass":1,"photoUrl":null,"place":"","pointUrl":null,"pressure":0,"projectNum":"测试编号002FS0012-02","recordStaffId":"63de63c0-5abc-11e9-91ed-00163e010059","recordUrl":null,"uploadStaffId":null,"reportNum":"","sampleNum":"","samplingPurpose":"","standard":"《医用X射线诊断放射防护要求》GBZ 130-2013,《医用常规X射线诊断设备质量控制检测规范》WS 76-2017","sysStandard":",,,,,,,,,","temperature":0,"testingProject":"X、γ射线剂量率","testingWay":"","timeDeixis":"","monitorParameter":"","monitorObjectName":"","monitorObjectAddress":"","antennaHeight":"","unitUrl":null,"unusable":0,"weather":"","windSpeed":0,"xRayNum":"","projectId":"6c9393e6-ba16-11ea-831a-00163e067057","subCompanyId":"1","address":"浙江省杭州市余杭区未来科技处","taskNum":2,"staffMakeId":null,"objectWork":"","reason":"测","city":"杭州市","district":"余杭区","province":"浙江省","nuclideTime":null,"enterTime":"2020-06-29 22:45:23","chartId":null,"carNum":"","noPass":0,"docReason":null,"isDh":0,"deviceType":null,"startTime":"2020-06-29 22:46:17","endTime":"2020-06-30 11:04:55","checkTime":"2020-06-30 11:05:12","uploadTime":null,"deviceFrequency":null,"testingFrequency":null,"testingPurpose":"卫生验收","isBc":1,"taskTestProjectList":"[{\"testProjectName\":\"project_fs_fh\",\"testProjectArr\":[{\"name\":\"projcet_gzwyzwtgxdk\"},{\"name\":\"projcet_jfcsl\"},{\"name\":\"projcet_jcjg\"},{\"name\":\"projcet_szpbt\"},{\"name\":\"projcet_gzltj\"},{\"name\":\"projcet_szwjcjlmkt\"},{\"name\":\"projcet_szwjcjlmknr\"},{\"name\":\"projcet_jcbt\"},{\"name\":\"projcet_jcbnr\"},{\"name\":\"projcet_jgyst\"},{\"name\":\"projcet_jgysnr\"}],\"testProjectId\":\"69041af5-ef38-11e9-a9b3-00163e010059\",\"testProjectChineseName\":\"机房周围剂量当量率\",\"testProjectType\":1,\"consumablesName\":null,\"consumablesSize\":0,\"xcStandardName\":\"《医用X射线诊断放射防护要求》\",\"testProjectNum\":\"GBZ 130-2013\",\"xcStandardNum\":\"GBZ 130-2013\",\"standardUseTerms\":\"7.2\",\"detectionLimitPieces\":\"null\",\"planTestingSize\":1,\"toShow\":true,\"blankSize\":0,\"name\":\"project_fs_fh\"},{\"testProjectName\":\"project_ts_tssjzrstbkqbsdnldxz\",\"testProjectArr\":[{\"name\":\"project_ts_tssjzrstbkqbsdnldxz1\"},{\"name\":\"project_ts_tssjzrstbkqbsdnldxz2\"}],\"testProjectId\":\"fabac3dd-6b1d-11ea-831a-00163e067057\",\"testProjectChineseName\":\"透视-透视受检者入射体表空气比释动能率典型值\",\"testProjectType\":1,\"consumablesName\":null,\"consumablesSize\":0,\"xcStandardName\":\"《医用常规X射线诊断设备质量控制检测规范》\",\"testProjectNum\":\"001235\",\"xcStandardNum\":\"WS 76-2017\",\"standardUseTerms\":\"（7.1）\",\"detectionLimitPieces\":\"\",\"planTestingSize\":1,\"toShow\":true,\"blankSize\":0,\"name\":\"project_ts_tssjzrstbkqbsdnldxz\"},{\"testProjectName\":\"project_ts_tssjzrstbkqbsdnlzdz\",\"testProjectArr\":[{\"name\":\"project_ts_tssjzrstbkqbsdnlzdz1\"},{\"name\":\"project_ts_tssjzrstbkqbsdnlzdz2\"}],\"testProjectId\":\"100e50c6-6b1e-11ea-831a-00163e067057\",\"testProjectChineseName\":\"透视-透视受检者入射体表空气比释动能率最大值\",\"testProjectType\":1,\"consumablesName\":null,\"consumablesSize\":0,\"xcStandardName\":\"《医用常规X射线诊断设备质量控制检测规范》\",\"testProjectNum\":\"001523\",\"xcStandardNum\":\"WS 76-2017\",\"standardUseTerms\":\"（7.2）\",\"detectionLimitPieces\":\"\",\"planTestingSize\":1,\"toShow\":true,\"blankSize\":0,\"name\":\"project_ts_tssjzrstbkqbsdnlzdz\"},{\"testProjectName\":\"project_ts_tsygplmd\",\"testProjectArr\":[{\"name\":\"project_ts_tsygplmd1\"},{\"name\":\"project_ts_tsygplmd2\"}],\"testProjectId\":\"2421cb45-6b1e-11ea-831a-00163e067057\",\"testProjectChineseName\":\"透视-透视荧光屏灵敏度\",\"testProjectType\":1,\"consumablesName\":null,\"consumablesSize\":0,\"xcStandardName\":\"《医用常规X射线诊断设备质量控制检测规范》\",\"testProjectNum\":\"464611\",\"xcStandardNum\":\"WS 76-2017\",\"standardUseTerms\":\"（7.3）\",\"detectionLimitPieces\":\"\",\"planTestingSize\":1,\"toShow\":true,\"blankSize\":0,\"name\":\"project_ts_tsygplmd\"},{\"testProjectName\":\"projcet_ts_kjfbl\",\"testProjectArr\":[{\"name\":\"projcet_ts_kjfbl1\"},{\"name\":\"projcet_ts_kjfbl2\"}],\"testProjectId\":\"37cd3a5a-6b1e-11ea-831a-00163e067057\",\"testProjectChineseName\":\"透视-空间分辨力\",\"testProjectType\":1,\"consumablesName\":null,\"consumablesSize\":0,\"xcStandardName\":\"《医用常规X射线诊断设备质量控制检测规范》\",\"testProjectNum\":\"144254\",\"xcStandardNum\":\"WS 76-2017\",\"standardUseTerms\":\"（7.5）\",\"detectionLimitPieces\":\"\",\"planTestingSize\":1,\"toShow\":true,\"blankSize\":0,\"name\":\"projcet_ts_kjfbl\"},{\"testProjectName\":\"project_ts_ddbfbl\",\"testProjectArr\":[{\"name\":\"project_ts_ddbfbl1\"},{\"name\":\"project_ts_ddbfbl2\"}],\"testProjectId\":\"49782881-6b1e-11ea-831a-00163e067057\",\"testProjectChineseName\":\"透视-低对比分辨力\",\"testProjectType\":1,\"consumablesName\":null,\"consumablesSize\":0,\"xcStandardName\":\"《医用常规X射线诊断设备质量控制检测规范》\",\"testProjectNum\":\"4946113\",\"xcStandardNum\":\"WS 76-2017\",\"standardUseTerms\":\"（7.5）\",\"detectionLimitPieces\":\"\",\"planTestingSize\":1,\"toShow\":true,\"blankSize\":0,\"name\":\"project_ts_ddbfbl\"},{\"testProjectName\":\"project_ts_yxjsqrspqkqbsdnl\",\"testProjectArr\":[{\"name\":\"project_ts_yxjsqrspqkqbsdnl1\"},{\"name\":\"project_ts_yxjsqrspqkqbsdnl2\"}],\"testProjectId\":\"5b0e081f-6b1e-11ea-831a-00163e067057\",\"testProjectChineseName\":\"透视-影像接收器入射屏前空气比释动能率\",\"testProjectType\":1,\"consumablesName\":null,\"consumablesSize\":0,\"xcStandardName\":\"《医用常规X射线诊断设备质量控制检测规范》\",\"testProjectNum\":\"4646131\",\"xcStandardNum\":\"WS 76-2017\",\"standardUseTerms\":\"（7.6）\",\"detectionLimitPieces\":\"\",\"planTestingSize\":1,\"toShow\":true,\"blankSize\":0,\"name\":\"project_ts_yxjsqrspqkqbsdnl\"},{\"testProjectName\":\"project_ts_zdldkz\",\"testProjectArr\":[{\"name\":\"project_ts_zdldkz1\"},{\"name\":\"project_ts_zdldkz2\"}],\"testProjectId\":\"6d24a4ac-6b1e-11ea-831a-00163e067057\",\"testProjectChineseName\":\"透视-自动亮度控制\",\"testProjectType\":1,\"consumablesName\":null,\"consumablesSize\":0,\"xcStandardName\":\"《医用常规X射线诊断设备质量控制检测规范》\",\"testProjectNum\":\"6461\",\"xcStandardNum\":\"WS 76-2017\",\"standardUseTerms\":\"（7.7）\",\"detectionLimitPieces\":\"\",\"planTestingSize\":1,\"toShow\":true,\"blankSize\":0,\"name\":\"project_ts_zdldkz\"},{\"testProjectName\":\"project_ts_zsyyyxjsqzxpc\",\"testProjectArr\":null,\"testProjectId\":\"83148145-6b1e-11ea-831a-00163e067057\",\"testProjectChineseName\":\"透视-照射野与影像接收器中心偏差\",\"testProjectType\":1,\"consumablesName\":null,\"consumablesSize\":0,\"xcStandardName\":\"《医用常规X射线诊断设备质量控制检测规范》\",\"testProjectNum\":\"4611\",\"xcStandardNum\":\"WS 76-2017\",\"standardUseTerms\":\"（7.8）\",\"detectionLimitPieces\":\"\",\"planTestingSize\":1,\"toShow\":true,\"blankSize\":0,\"name\":\"project_ts_zsyyyxjsqzxpc\"},{\"testProjectName\":\"project_ts_zdzsyyptygccxtsdhpj\",\"testProjectArr\":null,\"testProjectId\":\"97635d6e-6b1e-11ea-831a-00163e067057\",\"testProjectChineseName\":\"透视-最大照射野与普通荧光屏尺寸相同时的台屏距\",\"testProjectType\":1,\"consumablesName\":null,\"consumablesSize\":0,\"xcStandardName\":\"《医用常规X射线诊断设备质量控制检测规范》\",\"testProjectNum\":\"761251\",\"xcStandardNum\":\"WS 76-2017\",\"standardUseTerms\":\"（1.0）\",\"detectionLimitPieces\":\"\",\"planTestingSize\":1,\"toShow\":true,\"blankSize\":0,\"name\":\"project_ts_zdzsyyptygccxtsdhpj\"}]","materialStaffId":null,"testProjectList":"[{\"testProjectName\":\"project_fs_fh\",\"testProjectArr\":[{\"name\":\"projcet_gzwyzwtgxdk\"},{\"name\":\"projcet_jfcsl\"},{\"name\":\"projcet_jcjg\"},{\"name\":\"projcet_szpbt\"},{\"name\":\"projcet_gzltj\"},{\"name\":\"projcet_szwjcjlmkt\"},{\"name\":\"projcet_szwjcjlmknr\"},{\"name\":\"projcet_jcbt\"},{\"name\":\"projcet_jcbnr\"},{\"name\":\"projcet_jgyst\"},{\"name\":\"projcet_jgysnr\"}],\"testProjectId\":\"69041af5-ef38-11e9-a9b3-00163e010059\",\"testProjectChineseName\":\"机房周围剂量当量率\",\"testProjectType\":1,\"consumablesName\":null,\"consumablesSize\":0,\"xcStandardName\":\"《医用X射线诊断放射防护要求》\",\"testProjectNum\":\"GBZ 130-2013\",\"xcStandardNum\":\"GBZ 130-2013\",\"standardUseTerms\":\"7.2\",\"detectionLimitPieces\":\"null\",\"planTestingSize\":1,\"toShow\":true,\"blankSize\":0,\"name\":\"project_fs_fh\"},{\"testProjectName\":\"project_ts_tssjzrstbkqbsdnldxz\",\"testProjectArr\":[{\"name\":\"project_ts_tssjzrstbkqbsdnldxz1\"},{\"name\":\"project_ts_tssjzrstbkqbsdnldxz2\"}],\"testProjectId\":\"fabac3dd-6b1d-11ea-831a-00163e067057\",\"testProjectChineseName\":\"透视-透视受检者入射体表空气比释动能率典型值\",\"testProjectType\":1,\"consumablesName\":null,\"consumablesSize\":0,\"xcStandardName\":\"《医用常规X射线诊断设备质量控制检测规范》\",\"testProjectNum\":\"001235\",\"xcStandardNum\":\"WS 76-2017\",\"standardUseTerms\":\"（7.1）\",\"detectionLimitPieces\":\"\",\"planTestingSize\":1,\"toShow\":true,\"blankSize\":0,\"name\":\"project_ts_tssjzrstbkqbsdnldxz\"},{\"testProjectName\":\"project_ts_tssjzrstbkqbsdnlzdz\",\"testProjectArr\":[{\"name\":\"project_ts_tssjzrstbkqbsdnlzdz1\"},{\"name\":\"project_ts_tssjzrstbkqbsdnlzdz2\"}],\"testProjectId\":\"100e50c6-6b1e-11ea-831a-00163e067057\",\"testProjectChineseName\":\"透视-透视受检者入射体表空气比释动能率最大值\",\"testProjectType\":1,\"consumablesName\":null,\"consumablesSize\":0,\"xcStandardName\":\"《医用常规X射线诊断设备质量控制检测规范》\",\"testProjectNum\":\"001523\",\"xcStandardNum\":\"WS 76-2017\",\"standardUseTerms\":\"（7.2）\",\"detectionLimitPieces\":\"\",\"planTestingSize\":1,\"toShow\":true,\"blankSize\":0,\"name\":\"project_ts_tssjzrstbkqbsdnlzdz\"},{\"testProjectName\":\"project_ts_tsygplmd\",\"testProjectArr\":[{\"name\":\"project_ts_tsygplmd1\"},{\"name\":\"project_ts_tsygplmd2\"}],\"testProjectId\":\"2421cb45-6b1e-11ea-831a-00163e067057\",\"testProjectChineseName\":\"透视-透视荧光屏灵敏度\",\"testProjectType\":1,\"consumablesName\":null,\"consumablesSize\":0,\"xcStandardName\":\"《医用常规X射线诊断设备质量控制检测规范》\",\"testProjectNum\":\"464611\",\"xcStandardNum\":\"WS 76-2017\",\"standardUseTerms\":\"（7.3）\",\"detectionLimitPieces\":\"\",\"planTestingSize\":1,\"toShow\":true,\"blankSize\":0,\"name\":\"project_ts_tsygplmd\"},{\"testProjectName\":\"projcet_ts_kjfbl\",\"testProjectArr\":[{\"name\":\"projcet_ts_kjfbl1\"},{\"name\":\"projcet_ts_kjfbl2\"}],\"testProjectId\":\"37cd3a5a-6b1e-11ea-831a-00163e067057\",\"testProjectChineseName\":\"透视-空间分辨力\",\"testProjectType\":1,\"consumablesName\":null,\"consumablesSize\":0,\"xcStandardName\":\"《医用常规X射线诊断设备质量控制检测规范》\",\"testProjectNum\":\"144254\",\"xcStandardNum\":\"WS 76-2017\",\"standardUseTerms\":\"（7.5）\",\"detectionLimitPieces\":\"\",\"planTestingSize\":1,\"toShow\":true,\"blankSize\":0,\"name\":\"projcet_ts_kjfbl\"},{\"testProjectName\":\"project_ts_ddbfbl\",\"testProjectArr\":[{\"name\":\"project_ts_ddbfbl1\"},{\"name\":\"project_ts_ddbfbl2\"}],\"testProjectId\":\"49782881-6b1e-11ea-831a-00163e067057\",\"testProjectChineseName\":\"透视-低对比分辨力\",\"testProjectType\":1,\"consumablesName\":null,\"consumablesSize\":0,\"xcStandardName\":\"《医用常规X射线诊断设备质量控制检测规范》\",\"testProjectNum\":\"4946113\",\"xcStandardNum\":\"WS 76-2017\",\"standardUseTerms\":\"（7.5）\",\"detectionLimitPieces\":\"\",\"planTestingSize\":1,\"toShow\":true,\"blankSize\":0,\"name\":\"project_ts_ddbfbl\"},{\"testProjectName\":\"project_ts_yxjsqrspqkqbsdnl\",\"testProjectArr\":[{\"name\":\"project_ts_yxjsqrspqkqbsdnl1\"},{\"name\":\"project_ts_yxjsqrspqkqbsdnl2\"}],\"testProjectId\":\"5b0e081f-6b1e-11ea-831a-00163e067057\",\"testProjectChineseName\":\"透视-影像接收器入射屏前空气比释动能率\",\"testProjectType\":1,\"consumablesName\":null,\"consumablesSize\":0,\"xcStandardName\":\"《医用常规X射线诊断设备质量控制检测规范》\",\"testProjectNum\":\"4646131\",\"xcStandardNum\":\"WS 76-2017\",\"standardUseTerms\":\"（7.6）\",\"detectionLimitPieces\":\"\",\"planTestingSize\":1,\"toShow\":true,\"blankSize\":0,\"name\":\"project_ts_yxjsqrspqkqbsdnl\"},{\"testProjectName\":\"project_ts_zdldkz\",\"testProjectArr\":[{\"name\":\"project_ts_zdldkz1\"},{\"name\":\"project_ts_zdldkz2\"}],\"testProjectId\":\"6d24a4ac-6b1e-11ea-831a-00163e067057\",\"testProjectChineseName\":\"透视-自动亮度控制\",\"testProjectType\":1,\"consumablesName\":null,\"consumablesSize\":0,\"xcStandardName\":\"《医用常规X射线诊断设备质量控制检测规范》\",\"testProjectNum\":\"6461\",\"xcStandardNum\":\"WS 76-2017\",\"standardUseTerms\":\"（7.7）\",\"detectionLimitPieces\":\"\",\"planTestingSize\":1,\"toShow\":true,\"blankSize\":0,\"name\":\"project_ts_zdldkz\"},{\"testProjectName\":\"project_ts_zsyyyxjsqzxpc\",\"testProjectArr\":null,\"testProjectId\":\"83148145-6b1e-11ea-831a-00163e067057\",\"testProjectChineseName\":\"透视-照射野与影像接收器中心偏差\",\"testProjectType\":1,\"consumablesName\":null,\"consumablesSize\":0,\"xcStandardName\":\"《医用常规X射线诊断设备质量控制检测规范》\",\"testProjectNum\":\"4611\",\"xcStandardNum\":\"WS 76-2017\",\"standardUseTerms\":\"（7.8）\",\"detectionLimitPieces\":\"\",\"planTestingSize\":1,\"toShow\":true,\"blankSize\":0,\"name\":\"project_ts_zsyyyxjsqzxpc\"},{\"testProjectName\":\"project_ts_zdzsyyptygccxtsdhpj\",\"testProjectArr\":null,\"testProjectId\":\"97635d6e-6b1e-11ea-831a-00163e067057\",\"testProjectChineseName\":\"透视-最大照射野与普通荧光屏尺寸相同时的台屏距\",\"testProjectType\":1,\"consumablesName\":null,\"consumablesSize\":0,\"xcStandardName\":\"《医用常规X射线诊断设备质量控制检测规范》\",\"testProjectNum\":\"761251\",\"xcStandardNum\":\"WS 76-2017\",\"standardUseTerms\":\"（1.0）\",\"detectionLimitPieces\":\"\",\"planTestingSize\":1,\"toShow\":true,\"blankSize\":0,\"name\":\"project_ts_zdzsyyptygccxtsdhpj\"}]","isDocImg":0,"deviceTypeName":"X射线透视设备","deviceMainId":"1","headTestProjectName":"project_jcxcxx","businessLicenseNum":"91440300074380587M","metrologicalCertificate":"201719120948","mechanismName":"深圳市瑞达检测技术有限公司","subCompanyAddress":"深圳市龙华区民治街道上芬社区第五工业区二区4号201","staffName":"test1,test2"}]},"isCreate":true}